{"abGroup": 0, "abUseExperiments": [{"experimentName": "aud_desktop_aud3558_expert_opinion_gpt", "groupName": "C"}, {"experimentName": "newbuilding_flatsale_trap_desktop", "groupName": "B"}, {"experimentName": "newbuilding_new_entry_point_webim_desktop", "groupName": "A"}, {"experimentName": "newbuilding_rent_trap_desktop", "groupName": "C"}, {"experimentName": "newbuilding_suburban_trap_desktop", "groupName": "B"}, {"experimentName": "newbuilding_trust_safety_desktop", "groupName": "enabled"}], "aside": {"height": 0, "isNavigationActive": false, "activeAnchor": "#photos", "isCompactModeEnabled": false}, "hideOffer": {}, "bookedOfferId": 0, "captchaSiteKey": "6LfvfCETAAAAABxHQ2wxiTT_mILt0c87axZn7zOU", "captchaSpamSiteKey": "6LdpqSQUAAAAAJXo9mQJY2QYw2rSi2D0-ZXctcw_", "commentsData": {"commentText": "", "editing": false, "isOpen": false, "messageError": "", "statusFetch": "none", "openAfterAuth": false}, "favoriteMotivation": {"isActive": true, "isShows": false}, "feedback": {"isComplaintPopupOpened": false, "isFeedbackSent": false, "isFeedbackSentPopupOpened": false, "isFormPopupOpened": false, "isPopupOpened": false, "status": "Initial"}, "gallery": {}, "legend": {"isOpen": false}, "mapSimilar": null, "mapTabs": {"activeTab": "similarOffers"}, "mortgage": {"rates": {"flat": {"used": 22.49, "new": 5.99}, "appartments": {"used": 22.99, "new": 22.99}, "suburban": {"new": 6, "used": 25.9}}, "bankIds": ["bank-alfa", "bank-domrf", "bank-mkb", "bank-sovcom", "bank-t", "bank-uralsib", "bank-vtb-new"]}, "mortgageGallery": {}, "newbuildingBookedFromDeveloper": {"isConfirmOpen": false, "status": "initial"}, "newbuildingChat": {"userData": null, "isOpen": false}, "newbuildingConsultant": {"accountName": "cianru008", "consultantPhoneEnabledRegions": [1, 4593, -1], "location": "reserve"}, "offerChat": {"isChatsEnabled": true, "isChatOpened": false, "openAfterAuth": false, "isOnline": false, "hintQuestions": [{"analyticsKey": "contactMe", "buttonText": "Свяжитесь со мной", "messageText": "Здравствуйте. Пожалуйста, свяжитесь со мной ", "payload": null}, {"analyticsKey": "isActual", "buttonText": "Ещё сдаёте?", "messageText": "Здравствуйте. Уточните, пожалуйста, ещё сдаёте?", "payload": null}, {"analyticsKey": "whenSee", "buttonText": "Хочу посмотреть", "messageText": "Здравствуйте. Подскажите, пожалуйста, когда можно посмотреть квартиру?", "payload": null}]}, "offerData": {"offer": {"category": "flatRent", "status": "published", "dealType": "rent", "offerType": "flat", "geo": {"address": [{"fullName": "Москва", "id": 1, "locationTypeId": 1, "name": "Москва", "shortName": "Москва", "type": "location", "url": "https://www.cian.ru/snyat-4-komnatnuyu-kvartiru/"}, {"fullName": "ЗАО", "id": 11, "locationTypeId": -1, "name": "ЗАО", "shortName": "ЗАО", "type": "okrug", "url": "https://www.cian.ru/snyat-4-komnatnuyu-kvartiru-moskva-zao-0411/"}, {"fullName": "район Дорогомилово", "id": 113, "locationTypeId": -1, "name": "Дорогомилово", "shortName": "р-н Дорогомилово", "type": "raion", "url": "https://www.cian.ru/snyat-4-komnatnuyu-kvartiru-moskva-dorogomilovo-04113/"}, {"fullName": "Дохтуровский переулок", "id": 999, "locationTypeId": -1, "name": "Дохтуровский", "shortName": "Дохтуровский пер.", "type": "street", "url": "https://www.cian.ru/snyat-4-komnatnuyu-kvartiru-moskva-dohturovskiy-pereulok-02999/"}, {"fullName": "6", "id": 1692053, "locationTypeId": -1, "name": "6", "shortName": "6", "type": "house", "url": "https://www.cian.ru/cat.php?deal_type=rent&engine_version=2&house%5B0%5D=1692053&offer_type=flat&room4=1&type=4"}], "coordinates": {"lat": 55.742042, "lng": 37.552498}, "highways": [], "jk": {"id": 93, "name": "Кутузовский", "house": {"id": 2038, "name": "Дохтуровский переулок 6"}, "gaGeo": {"moId": 0, "oblId": 1, "cityId": 1}, "fullUrl": "https://www.cian.ru/zhiloy-kompleks-kutuzovskiy-moskva-93/", "fullUrlTemplate": "{request_scheme}://zhk-kutuzovskiy-i.{host}/"}, "railways": [{"id": 693, "directionIds": [14], "distance": "1.0", "time": 2, "name": "Москва (Киевский вокзал)", "travelType": "byCar"}, {"id": 693, "directionIds": [14], "distance": "1.0", "time": 14, "name": "Москва (Киевский вокзал)", "travelType": "byFoot"}, {"id": 707, "directionIds": [11], "distance": "2.0", "time": 33, "name": "Тестовская", "travelType": "byFoot"}, {"id": 708, "directionIds": [11], "distance": "3.0", "time": 42, "name": "Фили", "travelType": "byFoot"}, {"id": 707, "directionIds": [11], "distance": "4.0", "time": 7, "name": "Тестовская", "travelType": "byCar"}, {"id": 708, "directionIds": [11], "distance": "7.0", "time": 11, "name": "Фили", "travelType": "byCar"}], "undergrounds": [{"id": 120, "name": "Студенческая", "lineColor": "009BD5", "travelType": "walk", "travelTime": 8, "url": "https://www.cian.ru/snyat-4-komnatnuyu-kvartiru-moskva-metro-studencheskaya/", "underConstruction": false}, {"id": 46, "name": "Киевская", "lineColor": "03238B", "travelType": "walk", "travelTime": 11, "url": "https://www.cian.ru/snyat-4-komnatnuyu-kvartiru-moskva-metro-kievskaya/", "underConstruction": false}, {"id": 62, "name": "Кутузовская", "lineColor": "009BD5", "travelType": "walk", "travelTime": 18, "url": "https://www.cian.ru/snyat-4-komnatnuyu-kvartiru-moskva-stanciya-mck-kutuzovskaya/", "underConstruction": false}]}, "id": 309132307, "objectGuid": "4f9d7003-2cfa-4023-a573-26750815742a", "cianId": 309132307, "userId": 19502447, "publishedUserId": 121885927, "cianUserId": 121885927, "description": "Лот 553619. Бонус коллегам! Предлагается в аренду светлая квартира в современном жилом доме бизнес-класса \"Кутузовский\". \n\nПланировка: кухня, гостиная с камином, основная спальня с совмещенной ванной комнатой и гардеробной, две спальни, одна из которых с совмещенным санузлом, прихожая, гостевой туалет, постирочная и просторная лоджия. Квартира полностью меблирована и оснащена всей необходимой бытовой техникой. Вывоз и докупка обсуждается.\n\nОгороженная и охраняемая территория дома, подземный паркинг, машиноместо оплачивается отдельно. PLEASE FEEL FREE TO CONTACT US TO GET DETAILED INFORMATION.\n\nНомер объекта: #1/553619/13367", "photos": [{"id": 2308024405, "isDefault": false, "fullUrl": "https://images.cdn-cian.ru/images/2308024405-1.jpg", "thumbnailUrl": "https://images.cdn-cian.ru/images/2308024405-2.jpg", "thumbnail2Url": "https://images.cdn-cian.ru/images/2308024405-4.jpg", "miniUrl": "https://images.cdn-cian.ru/images/2308024405-3.jpg", "isLayout": false, "isCianLayout": false}, {"id": 2308024408, "isDefault": false, "fullUrl": "https://images.cdn-cian.ru/images/2308024408-1.jpg", "thumbnailUrl": "https://images.cdn-cian.ru/images/2308024408-2.jpg", "thumbnail2Url": "https://images.cdn-cian.ru/images/2308024408-4.jpg", "miniUrl": "https://images.cdn-cian.ru/images/2308024408-3.jpg", "isLayout": false, "isCianLayout": false}, {"id": 2308024413, "isDefault": false, "fullUrl": "https://images.cdn-cian.ru/images/2308024413-1.jpg", "thumbnailUrl": "https://images.cdn-cian.ru/images/2308024413-2.jpg", "thumbnail2Url": "https://images.cdn-cian.ru/images/2308024413-4.jpg", "miniUrl": "https://images.cdn-cian.ru/images/2308024413-3.jpg", "isLayout": false, "isCianLayout": false}, {"id": 2308024420, "isDefault": false, "fullUrl": "https://images.cdn-cian.ru/images/2308024420-1.jpg", "thumbnailUrl": "https://images.cdn-cian.ru/images/2308024420-2.jpg", "thumbnail2Url": "https://images.cdn-cian.ru/images/2308024420-4.jpg", "miniUrl": "https://images.cdn-cian.ru/images/2308024420-3.jpg", "isLayout": false, "isCianLayout": false}, {"id": 2308024425, "isDefault": false, "fullUrl": "https://images.cdn-cian.ru/images/2308024425-1.jpg", "thumbnailUrl": "https://images.cdn-cian.ru/images/2308024425-2.jpg", "thumbnail2Url": "https://images.cdn-cian.ru/images/2308024425-4.jpg", "miniUrl": "https://images.cdn-cian.ru/images/2308024425-3.jpg", "isLayout": false, "isCianLayout": false}, {"id": 2308024429, "isDefault": false, "fullUrl": "https://images.cdn-cian.ru/images/2308024429-1.jpg", "thumbnailUrl": "https://images.cdn-cian.ru/images/2308024429-2.jpg", "thumbnail2Url": "https://images.cdn-cian.ru/images/2308024429-4.jpg", "miniUrl": "https://images.cdn-cian.ru/images/2308024429-3.jpg", "isLayout": false, "isCianLayout": false}, {"id": 2308024435, "isDefault": false, "fullUrl": "https://images.cdn-cian.ru/images/2308024435-1.jpg", "thumbnailUrl": "https://images.cdn-cian.ru/images/2308024435-2.jpg", "thumbnail2Url": "https://images.cdn-cian.ru/images/2308024435-4.jpg", "miniUrl": "https://images.cdn-cian.ru/images/2308024435-3.jpg", "isLayout": false, "isCianLayout": false}, {"id": 2308024441, "isDefault": false, "fullUrl": "https://images.cdn-cian.ru/images/2308024441-1.jpg", "thumbnailUrl": "https://images.cdn-cian.ru/images/2308024441-2.jpg", "thumbnail2Url": "https://images.cdn-cian.ru/images/2308024441-4.jpg", "miniUrl": "https://images.cdn-cian.ru/images/2308024441-3.jpg", "isLayout": false, "isCianLayout": false}, {"id": 2308024448, "isDefault": false, "fullUrl": "https://images.cdn-cian.ru/images/2308024448-1.jpg", "thumbnailUrl": "https://images.cdn-cian.ru/images/2308024448-2.jpg", "thumbnail2Url": "https://images.cdn-cian.ru/images/2308024448-4.jpg", "miniUrl": "https://images.cdn-cian.ru/images/2308024448-3.jpg", "isLayout": false, "isCianLayout": false}, {"id": 2308024455, "isDefault": false, "fullUrl": "https://images.cdn-cian.ru/images/2308024455-1.jpg", "thumbnailUrl": "https://images.cdn-cian.ru/images/2308024455-2.jpg", "thumbnail2Url": "https://images.cdn-cian.ru/images/2308024455-4.jpg", "miniUrl": "https://images.cdn-cian.ru/images/2308024455-3.jpg", "isLayout": false, "isCianLayout": false}, {"id": 2308024461, "isDefault": false, "fullUrl": "https://images.cdn-cian.ru/images/2308024461-1.jpg", "thumbnailUrl": "https://images.cdn-cian.ru/images/2308024461-2.jpg", "thumbnail2Url": "https://images.cdn-cian.ru/images/2308024461-4.jpg", "miniUrl": "https://images.cdn-cian.ru/images/2308024461-3.jpg", "isLayout": false, "isCianLayout": false}, {"id": 2308024469, "isDefault": false, "fullUrl": "https://images.cdn-cian.ru/images/2308024469-1.jpg", "thumbnailUrl": "https://images.cdn-cian.ru/images/2308024469-2.jpg", "thumbnail2Url": "https://images.cdn-cian.ru/images/2308024469-4.jpg", "miniUrl": "https://images.cdn-cian.ru/images/2308024469-3.jpg", "isLayout": false, "isCianLayout": false}, {"id": 2308024474, "isDefault": false, "fullUrl": "https://images.cdn-cian.ru/images/2308024474-1.jpg", "thumbnailUrl": "https://images.cdn-cian.ru/images/2308024474-2.jpg", "thumbnail2Url": "https://images.cdn-cian.ru/images/2308024474-4.jpg", "miniUrl": "https://images.cdn-cian.ru/images/2308024474-3.jpg", "isLayout": false, "isCianLayout": false}, {"id": 2308024478, "isDefault": false, "fullUrl": "https://images.cdn-cian.ru/images/2308024478-1.jpg", "thumbnailUrl": "https://images.cdn-cian.ru/images/2308024478-2.jpg", "thumbnail2Url": "https://images.cdn-cian.ru/images/2308024478-4.jpg", "miniUrl": "https://images.cdn-cian.ru/images/2308024478-3.jpg", "isLayout": false, "isCianLayout": false}, {"id": 2308024485, "isDefault": false, "fullUrl": "https://images.cdn-cian.ru/images/2308024485-1.jpg", "thumbnailUrl": "https://images.cdn-cian.ru/images/2308024485-2.jpg", "thumbnail2Url": "https://images.cdn-cian.ru/images/2308024485-4.jpg", "miniUrl": "https://images.cdn-cian.ru/images/2308024485-3.jpg", "isLayout": false, "isCianLayout": false}, {"id": 2308024491, "isDefault": false, "fullUrl": "https://images.cdn-cian.ru/images/2308024491-1.jpg", "thumbnailUrl": "https://images.cdn-cian.ru/images/2308024491-2.jpg", "thumbnail2Url": "https://images.cdn-cian.ru/images/2308024491-4.jpg", "miniUrl": "https://images.cdn-cian.ru/images/2308024491-3.jpg", "isLayout": false, "isCianLayout": false}, {"id": 2308024497, "isDefault": false, "fullUrl": "https://images.cdn-cian.ru/images/2308024497-1.jpg", "thumbnailUrl": "https://images.cdn-cian.ru/images/2308024497-2.jpg", "thumbnail2Url": "https://images.cdn-cian.ru/images/2308024497-4.jpg", "miniUrl": "https://images.cdn-cian.ru/images/2308024497-3.jpg", "isLayout": false, "isCianLayout": false}, {"id": 2308024501, "isDefault": false, "fullUrl": "https://images.cdn-cian.ru/images/2308024501-1.jpg", "thumbnailUrl": "https://images.cdn-cian.ru/images/2308024501-2.jpg", "thumbnail2Url": "https://images.cdn-cian.ru/images/2308024501-4.jpg", "miniUrl": "https://images.cdn-cian.ru/images/2308024501-3.jpg", "isLayout": false, "isCianLayout": false}, {"id": 2308024507, "isDefault": false, "fullUrl": "https://images.cdn-cian.ru/images/2308024507-1.jpg", "thumbnailUrl": "https://images.cdn-cian.ru/images/2308024507-2.jpg", "thumbnail2Url": "https://images.cdn-cian.ru/images/2308024507-4.jpg", "miniUrl": "https://images.cdn-cian.ru/images/2308024507-3.jpg", "isLayout": false, "isCianLayout": false}, {"id": 2308024511, "isDefault": false, "fullUrl": "https://images.cdn-cian.ru/images/2308024511-1.jpg", "thumbnailUrl": "https://images.cdn-cian.ru/images/2308024511-2.jpg", "thumbnail2Url": "https://images.cdn-cian.ru/images/2308024511-4.jpg", "miniUrl": "https://images.cdn-cian.ru/images/2308024511-3.jpg", "isLayout": false, "isCianLayout": false}, {"id": 2308024515, "isDefault": false, "fullUrl": "https://images.cdn-cian.ru/images/2308024515-1.jpg", "thumbnailUrl": "https://images.cdn-cian.ru/images/2308024515-2.jpg", "thumbnail2Url": "https://images.cdn-cian.ru/images/2308024515-4.jpg", "miniUrl": "https://images.cdn-cian.ru/images/2308024515-3.jpg", "isLayout": false, "isCianLayout": false}, {"id": 2308024519, "isDefault": false, "fullUrl": "https://images.cdn-cian.ru/images/2308024519-1.jpg", "thumbnailUrl": "https://images.cdn-cian.ru/images/2308024519-2.jpg", "thumbnail2Url": "https://images.cdn-cian.ru/images/2308024519-4.jpg", "miniUrl": "https://images.cdn-cian.ru/images/2308024519-3.jpg", "isLayout": false, "isCianLayout": false}, {"id": 2308024522, "isDefault": false, "fullUrl": "https://images.cdn-cian.ru/images/2308024522-1.jpg", "thumbnailUrl": "https://images.cdn-cian.ru/images/2308024522-2.jpg", "thumbnail2Url": "https://images.cdn-cian.ru/images/2308024522-4.jpg", "miniUrl": "https://images.cdn-cian.ru/images/2308024522-3.jpg", "isLayout": false, "isCianLayout": false}, {"id": 2308024524, "isDefault": false, "fullUrl": "https://images.cdn-cian.ru/images/2308024524-1.jpg", "thumbnailUrl": "https://images.cdn-cian.ru/images/2308024524-2.jpg", "thumbnail2Url": "https://images.cdn-cian.ru/images/2308024524-4.jpg", "miniUrl": "https://images.cdn-cian.ru/images/2308024524-3.jpg", "isLayout": true, "isCianLayout": false}], "phones": [{"countryCode": "+7", "number": "9152432655"}], "publishTerms": {"terms": [{"services": ["paid"], "days": 30, "type": "periodical", "tariffIdentificator": {"tariffId": 9847110, "tariffGridType": "servicePackageGroup"}}], "autoprolong": true}, "flatType": "rooms", "roomType": "separate", "isApartments": false, "totalArea": "164.0", "loggiasCount": 0, "balconiesCount": 1, "windowsViewType": "yardAndStreet", "separateWcsCount": 1, "combinedWcsCount": 2, "repairType": "design", "hasFridge": true, "hasDishwasher": true, "hasWasher": true, "hasFurniture": true, "hasKitchenFurniture": true, "hasTv": true, "hasInternet": true, "flags": {"isArchived": false, "isCommercialOwnershipVerified": false}, "specialty": {"types": [], "additionalTypes": []}, "isNeedHideExactAddress": false, "areaParts": [], "roomsCount": 4, "floorNumber": 8, "bargainTerms": {"price": 350000, "priceType": "all", "currency": "rur", "paymentPeriod": "monthly", "leaseTermType": "longTerm", "prepayMonths": 1, "deposit": 350000, "utilitiesTerms": {"includedInPrice": true, "price": 0}, "includedOptions": [], "clientFee": 0, "agentFee": 0, "prices": {"rur": 350000, "usd": 3966, "eur": 3823}, "depositPrices": {"rur": 350000, "usd": 3966, "eur": 3823}, "utilitiesTermsPrices": {"rur": 0, "usd": 0, "eur": 0}, "tags": []}, "building": {"materialType": "monolith", "floorsCount": 18, "buildYear": 2007, "parking": {"type": "underground"}, "series": "Индивидуальный проект", "totalArea": "164.0", "liftTypes": [], "cranageTypes": [], "passengerLiftsCount": 1, "cargoLiftsCount": 0, "houseMaterialType": "monolith"}, "editDate": "2025-03-02T05:26:10.863000+00:00", "humanizedEditDate": "сегодня, 05:26", "isInHiddenBase": false, "isObjectHidden": false, "isClosedVisibility": false, "videos": [], "demolishedInMoscowProgramm": false, "exportLinks": {"pdfUrl": "/export/pdf/rent/flat/309132307/", "docxUrl": "/export/docx/rent/flat/309132307/"}, "passengerLiftsCount": 1, "cargoLiftsCount": 0, "added": "сегодня, 05:26", "valueAddedServices": {"isStandard": false, "isTop3": false, "isPremium": false}, "categoriesIds": [1000, 1100, 1110, 1111], "publicationDate": 1729985032, "creationDate": "2024-10-27T02:23:52.65", "recoveryLink": "/razmestit-obyavlenie/309132307/?isFromXML=1", "isFromBuilder": false, "isFromSeller": false, "isFromLeadFactory": false, "trackingData": {"moId": 0, "oblId": 1, "cityId": 1, "fbRegion": "Москва", "fbCity": "Москва"}, "editPhoto": "/realty/add2.aspx?id=309132307&isFromXML=1", "newEdit": "/razmestit-obyavlenie/?realty_id=309132307&isFromXML=1", "certificate": "https://www.cian.ru/newobjects/cian/certification/get?announcementId=309132307", "edit": "/realty/add1.aspx?id=309132307&isFromXML=1", "similarOffersLink": "", "similarOffersCount": 0, "buildersIds": [8008], "isImported": true, "userConfirmedFix": false, "newbuilding": {"id": 93, "name": "Кутузовский", "house": {"isReliable": false, "isFinished": true, "finishDate": {"quarter": 4, "year": 2006}, "id": 2038, "name": "Дохтуровский переулок 6"}, "isFromDeveloper": false, "isFromBuilder": false, "isFromSeller": false, "isFromLeadFactory": false, "showJkReliableFlag": false, "isFichering": false, "isFicheringPlus": false, "isPremium": false, "newbuildingFeatures": {"imagesCount": 5, "firstImageUrl": "https://images.cdn-cian.ru/images/4/777/785/kutuzovskiy-moskva-jk-587777480-6.jpg", "videosCount": 0, "deadlineInfo": "Сдан"}, "isReliable": false, "isTariffPremium": false}, "timezone": 3, "isEnabledCallTracking": true, "callTrackingProvider": "mts", "isRentByParts": false, "isDuplicate": false, "userTrust": "involved", "userTrustLevel": "involved", "showWarningMessage": false, "moderationInfo": {"showContactWarningMessage": false}, "isUnique": false, "isUniqueCheckDate": "2025-03-01", "isCianPartner": false, "externalId": "553619", "isIllegalConstruction": false, "externalOfferUrl": "", "cianLayouts": null}, "seoLinks": [], "breadcrumbs": [{"url": "https://www.cian.ru/", "title": "Недвижимость в Москве"}, {"url": "https://www.cian.ru/snyat/", "title": "Аренда"}, {"url": "https://www.cian.ru/snyat-4-komnatnuyu-kvartiru/", "title": "Аренда 4-комнатных квартир в Москве"}, {"url": "https://www.cian.ru/snyat-4-komnatnuyu-kvartiru-moskva-zao-0411/", "title": "ЗАО"}, {"url": "https://www.cian.ru/snyat-4-komnatnuyu-kvartiru-moskva-dorogomilovo-04113/", "title": "Дорогомилово"}, {"url": "https://www.cian.ru/snyat-4-komnatnuyu-kvartiru-moskva-metro-studencheskaya/", "title": "метро Студенческая"}, {"url": "https://www.cian.ru/snyat-4-komnatnuyu-kvartiru-moskva-dohturovskiy-pereulok-02999/", "title": "Дохтуровский переулок"}], "similarOffersMapQs": "engine_version=2&deal_type=rent&offer_type=flat&region=1&minprice=297500&maxprice=402499&room4=1&room5=1&type=4", "similarNewObjects": [{"id": 312768794, "photoUrl": "https://images.cdn-cian.ru/images/2382431494-4.jpg", "roomTitle": "4-комн. кв", "addressStr": "Москва, 3-й Павелецкий проезд", "floor": 27, "floorn": 15, "kitchenArea": 6.7, "livingArea": 60.1, "priceRur": 32559150, "publishedUserId": 126988851, "totalArea": 88.5, "undergroundInfo": {"lineColor": "00701A", "name": "Павелецкая", "type": "mow"}}, {"id": 314126019, "photoUrl": "https://images.cdn-cian.ru/images/2414479247-4.jpg", "roomTitle": "4-комн. кв", "addressStr": "Москва, ул. Ивана Франко, 6", "floor": 29, "floorn": 26, "kitchenArea": 8, "livingArea": 68.6, "priceRur": 36250000, "publishedUserId": 19777524, "totalArea": 105.1, "undergroundInfo": {"lineColor": "03238B", "name": "Кунцевская", "type": "mow"}}, {"id": 312757769, "photoUrl": "https://images.cdn-cian.ru/images/2388733813-4.jpg", "roomTitle": "4-комн. кв", "addressStr": "Москва, Левел Звенигородская жилой комплекс", "floor": 64, "floorn": 50, "kitchenArea": 0, "livingArea": 70.1, "priceRur": 29349524, "publishedUserId": 116824801, "totalArea": 75.1, "undergroundInfo": {"lineColor": "FA6F9E", "name": "Хорошёво", "type": "mow"}}, {"id": 314356788, "photoUrl": "https://images.cdn-cian.ru/images/2416120301-4.jpg", "roomTitle": "4-комн. кв", "addressStr": "Москва, Шмитовский проезд, 39к9", "floor": 14, "floorn": 11, "kitchenArea": 17.6, "livingArea": 39.2, "priceRur": 34781490, "publishedUserId": 111521308, "totalArea": 76.2, "undergroundInfo": {"lineColor": "FA6F9E", "name": "Шелепиха", "type": "mow"}}, {"id": 292153909, "photoUrl": "https://images.cdn-cian.ru/images/2254351106-4.jpg", "roomTitle": "4-комн. кв", "addressStr": "Москва, Эмоушен жилой комплекс", "floor": 28, "floorn": 6, "kitchenArea": 15.3, "livingArea": 60.1, "priceRur": 34365700, "publishedUserId": 102163700, "totalArea": 85.7, "undergroundInfo": {"lineColor": "27303F", "name": "Звенигородская", "type": "mow"}}], "linkToMap": "https://www.cian.ru/map/?engine_version=2&deal_type=rent&offer_type=flat&region=1&minprice=297500&maxprice=402499&room4=1&room5=1&type=4&zoom=16&center=55.742042%2C37.552498", "isFavorite": false, "offerFoldersCount": 0, "subscription": {"isSubscribed": false}, "priceChanges": [{"changeTime": "2025-01-17T17:39:37.176915+00:00", "priceData": {"currency": "rur", "price": 350000, "paymentPeriod": "monthly"}}, {"changeTime": "2025-01-14T22:37:13.788083+00:00", "priceData": {"currency": "rur", "price": 335000, "paymentPeriod": "monthly"}}, {"changeTime": "2024-12-05T17:37:15.196185+00:00", "priceData": {"currency": "rur", "price": 350000, "paymentPeriod": "monthly"}}, {"changeTime": "2024-11-26T22:11:15.166519+00:00", "priceData": {"currency": "rur", "price": 360000, "paymentPeriod": "monthly"}}, {"changeTime": "2024-11-08T18:25:32.982672+00:00", "priceData": {"currency": "rur", "price": 370000, "paymentPeriod": "monthly"}}, {"changeTime": "2024-10-28T11:50:42.008375+00:00", "priceData": {"currency": "rur", "price": 390000, "paymentPeriod": "monthly"}}, {"changeTime": "2024-10-26T23:23:53.761589+00:00", "priceData": {"currency": "rur", "price": 370000, "paymentPeriod": "monthly"}}], "newObject": {"name": "Кутузовский", "advantages": [], "specifications": [{"title": "Класс", "value": "Премиум"}, {"title": "Тип дома", "value": "Кирпичный"}, {"title": "Парковка", "value": ""}, {"title": "Отделка", "value": ""}, {"title": "Тип комплекса", "value": "Жилой комплекс", "valueTooltipText": "Один или несколько многоквартирных домов, объединённых общей территорией и инфраструктурой."}], "promoInfos": [], "decorations": [], "newbuildingFeatures": {"imagesCount": 5, "firstImageUrl": "https://images.cdn-cian.ru/images/4/777/785/kutuzovskiy-moskva-jk-587777480-6.jpg", "videosCount": 0, "reviewsCount": 0, "hasProgressOfConstructions": false}, "id": 93, "url": "/zhiloy-kompleks-kutuzovskiy-moskva-93/", "status": "Сдан", "developer": {"id": 8008, "url": "/zastroishchik-flet-i-ko-8008/", "name": "Флэт и Ко", "logoUrl": "/api/get-company-logo/?id=8008&rnd=950203", "stats": {"progress": {"qs": "builder=8008&deal_type=sale&engine_version=2&offer_type=newobject&status%5B0%5D=5002"}, "done": {"text": "13 домов в 10 ЖК", "qs": "builder=8008&deal_type=sale&engine_version=2&offer_type=newobject&show_old_newobjects=1&status%5B0%5D=5004"}}}, "hasLayoutImageOffers": false, "fullUrlWithSubdomain": "https://zhk-kutuzovskiy-i.cian.ru/", "gaLabel": "/sale/jk/mo_id=0/obl_id=1/city_id=1/object_type=2/ga_obj_type=0/spec=none/93/from_developer=1/nv=0/", "nearbyNewbuildingsMapUrl": "//cian.ru/map/?deal_type=sale&engine_version=2&zoom=12&with_newobject=1&newbuildings_search=true&region=1&center=55.74124309744363,37.551652103179734"}, "company": {"buildingStatus": [{"count": 10, "housesCount": 13, "statusId": 5004}], "categoryId": 2002, "description": "ООО «ФЛЭТ и Ко» образовано в 1996 году. Начав свою деятельность как агентство недвижимости, к 1999 году компания стала принимать участие в подрядных работах при строительстве новостроек в Москве, одновременно развивая смежные направления бизнеса.", "fromDeveloperPropsCount": null, "hasSpecProject": false, "id": 8008, "isTest": false, "locationIds": [1], "logoUrl": "/api/get-company-logo/?id=8008&rnd=131852", "name": "Флэт и Ко", "newobjectsCount": 10, "offersCount": 0, "phones": [], "promoCount": 0, "specProjectNewobjectsCount": 0, "status": 12, "website": "http://flatco.ru/", "yearFoundation": 1996, "reviewStats": {"reviewCount": 72, "reviewCountText": "72 отзыва", "totalRate": 3.8}, "advantages": null, "buildersAuctionRank": null, "email": null, "emailForRequest": null, "headerImageUrl": null, "isReliable": false, "maxBet": null, "newbuildingIds": null, "stats": null, "url": "#", "workYears": null}, "offences": [], "bti": {"houseData": {"yearRelease": 2007, "houseMaterialType": "monolith", "floorMax": 18, "entrances": 1, "flatCount": 68, "isEmergency": false, "demolishedInMoscowProgramm": false, "houseHeatSupplyType": "central", "houseOverhaulFundType": "specialOrg", "houseGasSupplyType": "without", "houseOverlapType": "concrete", "lifts": 3, "seriesName": "Индивидуальный проект"}}, "stats": {"daily": 0, "total": 470, "totalViewsFormattedString": "470 просмотров, нет за сегодня", "totalUniqueViewsFormattedString": "249 уникальных"}, "notes": {}, "agent": {"id": 121885927, "cianUserId": 121885927, "realtyUserId": 121885927, "accountType": "specialist", "companyName": "Trust Realty", "creationDate": "2024-09-17T16:28:39.747000+00:00", "name": "Хаджар Исаева", "isPro": true, "phones": [{"confirmed": true}], "skills": [], "absoluteAvatarUrl": "https://www.cian.ru/api/get-avatar/?i=66670532&t=2&p=2&timestamp=1726579720", "absoluteMiniAvatarUrl": "https://www.cian.ru/api/get-avatar/?i=66670532&t=2&p=1&timestamp=1726579720", "isDeveloper": false, "firstName": "Хаджар", "lastName": "Исаева", "parentId": 19502447, "parentCianId": 19502447, "isRecidivist": false, "isUserOffersHasErrors": false, "offersCount": 203, "offersLink": "https://www.cian.ru/company/19502447/", "availableServices": {"isUploadsAvailable": true, "isCallTrackingAvailable": false, "isPhoneChangingAvailable": false, "isServicePackagesAvailable": false, "canUseHiddenBase": true}, "userType": "realtor_based", "removeCompetitor": false, "status": "hidden", "isSubAgent": true, "isMessagingEnabled": false, "isPassportVerified": false, "isSelfEmployed": false, "isPrivateBroker": false, "masterAgent": {"cianUserId": 19502447, "realtyUserId": 19502447, "absoluteAvatarUrl": "https://www.cian.ru/api/get-avatar/?i=4106428&t=2&p=2&timestamp=1736602489", "absoluteMiniAvatarUrl": "https://www.cian.ru/api/get-avatar/?i=4106428&t=2&p=1&timestamp=1736602489", "experience": "2007", "accountType": "agency", "creationDate": "2018-10-13T19:59:21.937000+00:00", "offersCount": 203}, "isCianPartner": false, "canShowOnline": false, "moderationInfo": {"qualityLevelInfo": {"levelSystemName": "high", "levelName": "Надёжный агент", "levelOrder": 3, "hasVerifiedDocuments": false, "highResponsibility": true, "isSuperAgent": false, "isSuperHost": false, "isBlocked": false, "showSuperHost": false, "showSuperAgent": false, "showHighResponsibility": true}, "isUserIdentified": false, "isUserIdentifiedByDocuments": true, "showUserIdentifiedByDocuments": true}, "isHidden": true, "metrics": [{"title": "На Циан", "value": "6 лет"}, {"title": "Объектов в работе", "value": "203"}], "agentLists": []}, "specialProject": {"id": "pik", "link": "https://www.cian.ru/map/?builder=9&deal_type=2&with_newobject=1&object_type=2&currency=2&center=55.77228091175091,37.581318235024824&zoom=11&engine_version=2&newbuildings_search=true&is_pik_promo=1&region=1"}, "user": {"isAuthenticated": false, "permissions": {"canModerateUsers": false, "canModerateAnnouncements": false, "canModerateAnnouncementsExpert": false, "canViewUsers": false, "canViewAnnouncements": false}, "ga": {"type": "", "balance": 0, "packages": [], "emailMd5": ""}}, "agentAvailability": {"userId": 19502447, "available": false, "message": "Напишите ему или позвоните в рабочее время.", "title": "Специалист работает с 7:00 по 0:00.", "availableFrom": "2025-03-02T07:00:00+03:00", "availableTo": "2025-03-03T00:00:00+03:00"}, "agentReviews": {"approvedReviewsCount": 2, "entityName": "", "entityRate": 1, "entityRateMax": 5, "entityRateMin": 5, "isNotificationDisabled": true, "isUserMobilePushSubscribed": false, "isUserSubscribed": false, "rateCounts": [{"count": 2, "rate": 5}, {"count": 0, "rate": 4}, {"count": 0, "rate": 3}, {"count": 0, "rate": 2}, {"count": 0, "rate": 1}], "reviews": [{"answers": [], "created": 1732819572, "dislikesCount": 0, "likesCount": 0, "moderation": {"date": 1732866506}, "rate": 5, "reviewId": "0a63067a-adb9-11ef-86fe-ea08b909d541", "status": "approved", "text": "Все прошло отлично, нашли объект. Потратили много времени, но Хаджар стоически выдержала такое большое количество просмотров. Спасибо)", "totalAnswers": 0, "updated": 1732819572, "user": {"avatarUrl": "https://www.cian.ru/avatar.axd?i=124315430&t=1&p=2", "id": 124315430, "name": "Каменскас Иван ", "socialNetworks": []}, "userLikeStatus": "unknown"}, {"answers": [], "created": 1733846458, "dislikesCount": 0, "likesCount": 0, "moderation": {"date": 1733911540}, "rate": 5, "reviewId": "f223dbec-b70f-11ef-b4ef-1e079126abee", "status": "approved", "text": "Все прошло отлично, Хаджар приводила много клиентов на просмотры, сдали в итоге через нее", "totalAnswers": 0, "updated": 1733846458, "user": {"avatarUrl": "https://www.cian.ru/avatar.axd?i=105090955&t=1&p=2", "id": 105090955, "name": "ID:105090955", "socialNetworks": []}, "userLikeStatus": "unknown"}], "subscriptionEmail": "", "totalCount": 2}, "isHiddenByUser": false, "degradationInfo": {}, "brandingLevel": "thirdLevel", "rosreestrInfoV2": {"showCheckedLabel": false}, "isOnlineRegistrationAvailable": false, "factoids": [{"title": "Общая площадь", "icon": "https://images.cdn-cian.ru/imgmobile/icons/offer_card/size.svg", "value": "164 м²"}, {"title": "Этаж", "icon": "https://images.cdn-cian.ru/imgmobile/icons/offer_card/floor.svg", "value": "8 из 18"}, {"title": "Год постройки", "icon": "https://images.cdn-cian.ru/imgmobile/icons/offer_card/build_year.svg", "value": "2007"}], "sidebar": [{"title": "Оплата ЖКХ", "value": "включена (без счётчиков)"}, {"title": "Залог", "value": "350 000 ₽"}, {"title": "Комиссии", "value": "нет"}, {"title": "Предоплата", "value": "1 месяц"}, {"title": "Срок аренды", "value": "от года"}], "features": [{"title": "О квартире", "id": "aboutFlat", "features": [{"value": "164 м²", "label": "Общая площадь"}, {"value": "Изолированная", "label": "Планировка"}, {"value": "2 совмещенных, 1 раздельный", "label": "Санузел"}, {"value": "1 балкон", "label": "Балкон/лоджия"}, {"value": "На улицу и двор", "label": "Вид из окон"}, {"value": "Дизайнерский", "label": "Ремонт"}]}, {"title": "О доме", "id": "aboutBuilding", "features": [{"value": "2007", "label": "Год постройки"}, {"value": "Индивидуальный проект", "label": "Строительная серия"}, {"value": "1 пассажирский", "label": "Количество лифтов"}, {"value": "Монолитный", "label": "Тип дома"}, {"value": "Железобетонные", "label": "Тип перекрытий"}, {"value": "Подземная", "label": "Парковка"}, {"value": "1", "label": "Подъезды"}, {"value": "Центральное", "label": "Отопление"}, {"value": "Нет", "label": "Аварийность"}]}], "seoData": {"socialNetworksTitle": {"full": "Сдаётся, 4-комнатная квартира, за 350 000 ₽/мес., 164.0 м², этаж 8/18", "short": "Сдаётся, 4-комн. кв., за 350 000 ₽/мес."}, "mainTitle": "Аренда четырехкомнатной квартиры 164.0м² Дохтуровский пер., 6, Москва, ЗАО, р-н Дорогомилово м. Студенческая - база ЦИАН, объявление 309132307", "description": "➜ Арендуйте четырехкомнатную квартиру площадью 164.0м² Дохтуровский пер., 6, Москва, ЗАО, р-н Дорогомилово м. Студенческая. Цена аренды - 350 000 руб. в месяц. Недвижимость на ЦИАН - объявление 309132307", "micromarking": {"@context": "https://schema.org/", "@type": "Product", "name": "", "image": ["https://images.cdn-cian.ru/images/2308024405-1.jpg", "https://images.cdn-cian.ru/images/2308024408-1.jpg", "https://images.cdn-cian.ru/images/2308024413-1.jpg", "https://images.cdn-cian.ru/images/2308024420-1.jpg", "https://images.cdn-cian.ru/images/2308024425-1.jpg", "https://images.cdn-cian.ru/images/2308024429-1.jpg", "https://images.cdn-cian.ru/images/2308024435-1.jpg", "https://images.cdn-cian.ru/images/2308024441-1.jpg", "https://images.cdn-cian.ru/images/2308024448-1.jpg", "https://images.cdn-cian.ru/images/2308024455-1.jpg", "https://images.cdn-cian.ru/images/2308024461-1.jpg", "https://images.cdn-cian.ru/images/2308024469-1.jpg", "https://images.cdn-cian.ru/images/2308024474-1.jpg", "https://images.cdn-cian.ru/images/2308024478-1.jpg", "https://images.cdn-cian.ru/images/2308024485-1.jpg", "https://images.cdn-cian.ru/images/2308024491-1.jpg", "https://images.cdn-cian.ru/images/2308024497-1.jpg", "https://images.cdn-cian.ru/images/2308024501-1.jpg", "https://images.cdn-cian.ru/images/2308024507-1.jpg", "https://images.cdn-cian.ru/images/2308024511-1.jpg", "https://images.cdn-cian.ru/images/2308024515-1.jpg", "https://images.cdn-cian.ru/images/2308024519-1.jpg", "https://images.cdn-cian.ru/images/2308024522-1.jpg", "https://images.cdn-cian.ru/images/2308024524-1.jpg"], "description": "Лот 553619. Бонус коллегам Предлагается в аренду светлая квартира в современном жилом доме бизнескласса Кутузовский. Планировка кухня, гостиная с камином, основная спальня с совмещенной ванной комнатой и гардеробной, две спальни, одна из которых с совмещенным санузлом, прихожая, гостевой туалет, постирочная и просторная лоджия. Квартира полностью меблирована и оснащена всей необходимой бытовой техникой. Вывоз и докупка обсуждается.Огороженная и охраняемая территория дома, подземный паркинг, машиноместо оплачивается отдельно. PLEASE FEEL FREE TO CONTACT US TO GET DETAILED INFORMATION.Номер объекта 155361913367", "sku": 309132307, "brand": {"@type": "Brand", "name": "Циан"}, "review": {"@type": "Review", "reviewRating": {"@type": "Rating", "ratingValue": 4.9, "bestRating": 5}, "author": {"@type": "Person", "name": "Хаджар Исаева"}}, "offers": {"@type": "Offer", "url": "https://www.cian.ru/rent/flat/309132307/", "priceCurrency": "RUB", "availability": "https://schema.org/InStock", "price": 350000}}}, "trackingUrl": "/rent/flat/JK/obl_id=1/city_id=1/object_type=/ga_obj_type=4/rent_type=long/spec=agent/309132307/from_developer=0/repres=0/owner=0/pod_snos=0/nv=0/", "amenities": [{"title": "В квартире есть", "id": "flatRent", "amenities": [{"value": "Холодильник", "theme": "fridge"}, {"value": "Посудомоечная машина", "theme": "dishwasher"}, {"value": "Стиральная машина", "theme": "washing"}, {"value": "Телевизор", "theme": "tv"}, {"value": "Интернет", "theme": "internet"}, {"value": "Мебель на кухне", "theme": "kitchen"}, {"value": "Мебель в комнатах", "theme": "furniture"}]}], "newbuildingRating": 0, "offerPrice": "350 000 ₽/мес."}, "promotionsVillageData": {}, "offerStatsPopup": {"dataStats": null, "isOpen": false, "messageError": "", "statusFetch": 0}, "pageData": {"dealType": "rent", "offerId": 309132307, "offerType": "flat", "subdomain": "www"}, "phoneCollapse": false, "phoneWarning": {"isOpen": false, "target": null}, "printModal": {"isCommentsVisible": true, "isOpen": false, "isPhonesVisible": true, "isPrintModeEnabled": false}, "pushSubscribed": false, "reclaimModal": {"errorMessage": "", "isOpen": false, "statusFetch": "none"}, "remove": {"activeFrame": "initial", "isOpen": false, "status": "default"}, "seoLinks": {"isLoad": false, "seoLinks": {"seoBlocks": [{"title": "Дополнительные предложения по аренде", "links": [{"name": "4-комнатные квартиры снять квартиру возле парка", "uri": "/snyat-4-komnatnuyu-kvartiru-vozle-parka-sheremetevskaya-dubrava/"}, {"name": "4-комнатные квартиры снять квартиру возле парка", "uri": "/snyat-4-komnatnuyu-kvartiru-vozle-parka-dyusseldorfskii/"}, {"name": "4-комнатные квартиры снять квартиру возле парка", "uri": "/snyat-4-komnatnuyu-kvartiru-vozle-parka-3-go-mikroraiona-goroda-moskovskogo/"}]}]}}, "serviceBaseUrl": "https://service.cian.ru/", "similarOffers": {"userBased": {"list": [], "withoutCompetitors": false, "modelVersion": ""}, "itemBased": {"list": [], "withoutCompetitors": false, "modelVersion": ""}, "historyBased": {"list": [], "withoutCompetitors": false, "modelVersion": ""}, "newItemBased": {"list": [], "withoutCompetitors": false, "modelVersion": ""}, "newobjectItemBased": {"list": [], "withoutCompetitors": false, "modelVersion": ""}}, "specialPromoInfo": null, "subscriptionPriceChangesPopup": {"error": "", "isEmailConfirmed": false, "isOpen": false, "statusFetch": "none"}, "tracking": {"user": {"abGroup": 0, "type": "not_authorized"}, "page": {"customPageURL": "/rent/flat/mo_id=0/obl_id=1/city_id=1/object_type=/ga_obj_type=4/rent_type=long/spec=agent/309132307/from_developer=0/repres=0/owner=0/pod_snos=0/nv=0/", "dealType": "rent_long", "objectType": "flat_old", "offerID": 309132307, "offerPhone": "+79152432655", "pageType": "Card", "region": "0-1-1", "siteType": "desktop", "breadCrumbs": ["Недвижимость в Москве", "Аренда", "Аренда 4-комнатных квартир в Москве", "ЗАО", "Дорогомилово", "метро Студенческая", "Дохтуровский переулок"], "extra": {"category": "flatRent", "adfox": {"status": 0}}}}, "viewedSimilar": {"ids": []}, "ebcInfo": {"user": {"abGroup": 0, "isAuthorized": false}, "page": {"breadCrumbs": ["Недвижимость в Москве", "Аренда", "Аренда 4-комнатных квартир в Москве", "ЗАО", "Дорогомилово", "метро Студенческая", "Дохтуровский переулок"], "offerID": 309132307}}, "mlSearchRegions": [], "isMlSearchForAllEnabled": true, "isBrandingAvailable": true, "isCountrysideOffersBuilderBadgeEnabled": true, "isHomeowner": false, "soprApi": "https://sopr-api.cian.ru/", "widgetsMarkup": {}, "infrastructureMap": {"isLoaded": false}, "infrastructureCategories": [], "isCountrysidePromoEnabled": true, "knAuctionCompanies": [], "auctionBanks": [], "dealRent": {"isOpen": false, "isLoading": false, "error": null, "isSuccessModal": false, "isSendSimilarModal": false, "isSimilarSuccessModal": false, "isFailureModal": false, "isPrefetching": false, "phoneConfirmed": false, "isSendSMSLoading": false, "secondsToRetry": 60, "isEntryToShowOpen": false, "isEntryToShowSuccessModal": false, "initialFormState": {"personsCount": 1, "personsInfo": "", "childrenCount": 0, "childrenInfo": [], "petsCount": 0, "petsInfo": "", "comment": "", "activityScope": "", "name": "", "isAgent": false, "phone": "", "smsCode": ""}}, "renterForm": {"isOpen": false, "isLoading": false, "error": null, "isSuccessModal": false, "isFailureModal": false, "isPrefetching": false, "phoneConfirmed": false, "isSendSMSLoading": false, "secondsToRetry": 60, "currentStep": "onboarding", "initialFormState": {"personsCount": 1, "personsInfo": "", "childrenCount": 0, "childrenInfo": [], "petsCount": 0, "petsInfo": "", "comment": "", "activityScope": "", "name": "", "isAgent": false, "phone": "", "smsCode": ""}}, "complaintPopupOpen": false, "notAvailablePopupOpen": false, "featureToggle": {"utilitiesTermsSettings": {"isUtilitiesTermsEnabled": true, "useIncludeUtilitiesTermsRegions": true, "excludeUtilitiesTermsRegions": [4959, 4606, 4588, 2], "includeUtilitiesTermsRegions": [1, 4593]}, "newbuildingBlackFridaySettings": {"promoDatesText": ""}, "isFavoritesFolderEnabled": true, "isBuyAnalyticsButtonEnabled": false, "isLegalDocsUrlForCommercialReportsEnabled": true, "isCommercialNewVatTextEnabled": true, "isMortgageBrokerBannerEnabled": true, "newbuildingMortgageCalculatorMicrofrontEnabled": false, "isBestPlaceCheckoutEnabled": false, "isConsultantMessageButtonEnabled": true, "isChatOnboardingEnabled": false, "isWebimChatOnboardingEnabled": true}, "dealRentVasCost": 0, "isHomeownerDocsRequired": false, "offersHistory": {"data": {"listing": {"isFetching": false, "isError": false, "data": null, "isLoadMore": false}, "listingSpoiler": {"isFetching": false, "isError": false, "data": null, "isLoadMore": false}, "offers": {"isFetching": false, "isError": false, "isAuthError": false, "isLoadMore": false, "data": {}}}, "roomsFilterActiveValue": "all", "statusFilterActiveValue": "all", "page": 1, "resultsOnPage": 10, "activeOfferId": null, "isFiltersChanged": false, "viewedOffers": [], "defaultFilters": {}, "haveAdminAccess": false}, "offerValuation": {"data": null, "isFetching": false, "isError": false, "estimationPeriod": null}, "showAnalyticsButton": false, "entryToShowEnabled": false, "newStatsEnabled": false, "favoritesAssignWidget": {"folders": [], "selected": {}, "initialSelectedFolderIds": [], "savedOfferId": [], "savedInFolders": null, "userHasFolders": false, "showFoldersList": false, "showModalCreateFolder": false, "showOnBoardingDelete": false, "showNotification": false, "isListLoading": false, "canLoadMore": false}, "banksList": {"list": [{"id": "bank-sberbank", "enabled": false, "logo": "https://static.cdn-cian.ru/frontend/finance-assets/banks/logos/sber.svg", "icon": "https://static.cdn-cian.ru/frontend/finance-assets/bages/sber.svg", "name": "Сбербанк", "integration": "none"}, {"id": "bank-vtb-new", "enabled": true, "logo": "https://static.cdn-cian.ru/frontend/finance-assets/banks/logos/vtb.svg", "icon": "https://static.cdn-cian.ru/frontend/finance-assets/bages/vtb.svg", "fullsizeIcon": "https://static.cdn-cian.ru/frontend/finance-assets/fullsize/VTB_color.svg", "name": "ВТБ", "legalName": "Банк ВТБ (ПАО)", "integration": "custom", "inn": "7702070139"}, {"id": "bank-psb", "enabled": false, "logo": "https://static.cdn-cian.ru/frontend/finance-assets/banks/logos/psb.svg", "icon": "https://static.cdn-cian.ru/frontend/finance-assets/bages/psb.svg", "fullsizeIcon": "https://static.cdn-cian.ru/frontend/finance-assets/fullsize/PSB_color.svg", "name": "ПСБ", "legalName": "ПAO «Промсвязьбанк»", "integration": "none", "inn": "7744000912"}, {"id": "bank-gpb", "enabled": true, "logo": "https://static.cdn-cian.ru/frontend/finance-assets/banks/logos/gpb.svg", "icon": "https://static.cdn-cian.ru/frontend/finance-assets/bages/gazprom-bank.svg", "fullsizeIcon": "https://static.cdn-cian.ru/frontend/finance-assets/fullsize/GAZPROM_color.svg", "name": "Газпромбанк", "legalName": "Банк ГПБ (АО)", "integration": "light", "env": ["dev", "ote"], "inn": "7744001497"}, {"id": "bank-sovcom", "enabled": true, "logo": "https://static.cdn-cian.ru/frontend/finance-assets/banks/logos/sovcom.svg", "icon": "https://static.cdn-cian.ru/frontend/finance-assets/bages/sovkom-bank.svg", "fullsizeIcon": "https://static.cdn-cian.ru/frontend/finance-assets/fullsize/SOVKOMBANK_color.svg", "name": "Совкомбанк", "legalName": "ПАО «Совкомбанк»", "integration": "api", "inn": "4401116480"}, {"id": "bank-raif", "enabled": false, "logo": "https://static.cdn-cian.ru/frontend/finance-assets/banks/logos/raif.svg", "icon": "https://static.cdn-cian.ru/frontend/finance-assets/bages/raiffeisen-bank.svg", "fullsizeIcon": "https://static.cdn-cian.ru/frontend/finance-assets/fullsize/RAIFF_color.svg", "name": "Райффайзенбанк", "legalName": "АО «Райффайзенбанк»", "integration": "none", "inn": "7744000302"}, {"id": "bank-rshb", "enabled": false, "logo": "https://static.cdn-cian.ru/frontend/finance-assets/banks/logos/rshb.svg", "icon": "https://static.cdn-cian.ru/frontend/finance-assets/bages/rshb.svg", "fullsizeIcon": "https://static.cdn-cian.ru/frontend/finance-assets/fullsize/ROSSELHOZ_color.svg", "name": "Россельхозбанк", "legalName": "АО «Россельхозбанк»", "integration": "none", "inn": "7725114488"}, {"id": "bank-alfa", "enabled": true, "logo": "https://static.cdn-cian.ru/frontend/finance-assets/banks/logos/alfa.svg", "icon": "https://static.cdn-cian.ru/frontend/finance-assets/bages/alfa.svg", "fullsizeIcon": "https://static.cdn-cian.ru/frontend/finance-assets/fullsize/ALFA_color.svg", "name": "Альфа-Банк", "legalName": "АО «Альфа-Банк»", "integration": "light", "inn": "7728168971"}, {"id": "bank-bgf", "enabled": true, "logo": "https://static.cdn-cian.ru/frontend/finance-assets/banks/logos/bgf.svg", "icon": "https://static.cdn-cian.ru/frontend/finance-assets/bages/bgf.svg", "fullsizeIcon": "https://static.cdn-cian.ru/frontend/finance-assets/fullsize/BGF_color.svg", "name": "БЖФ", "notPayroll": true, "legalName": "АО «Банк БЖФ»", "integration": "api", "env": ["ote"], "inn": "7709056550"}, {"id": "bank-ubrir", "enabled": false, "logo": "https://static.cdn-cian.ru/frontend/finance-assets/banks/logos/ubrir.svg", "icon": "https://static.cdn-cian.ru/frontend/finance-assets/bages/ubrir.svg", "fullsizeIcon": "https://static.cdn-cian.ru/frontend/finance-assets/fullsize/UBRIR_color.svg", "name": "УБРиР", "legalName": "ПАО КБ «УБРИР»", "integration": "light", "inn": "6608008004"}, {"id": "bank-open", "enabled": false, "logo": "https://static.cdn-cian.ru/frontend/finance-assets/banks/logos/open.svg", "icon": "https://static.cdn-cian.ru/frontend/finance-assets/bages/open.svg", "fullsizeIcon": "https://static.cdn-cian.ru/frontend/finance-assets/fullsize/OPEN_color.svg", "name": "Открытие", "legalName": "ПАО Банк «ФК Открытие»", "integration": "none", "requireSpouseInfo": true, "inn": "7706092528"}, {"id": "bank-uralsib", "enabled": true, "logo": "https://static.cdn-cian.ru/frontend/finance-assets/banks/logos/uralsib.svg", "icon": "https://static.cdn-cian.ru/frontend/finance-assets/bages/uralsib.svg", "fullsizeIcon": "https://static.cdn-cian.ru/frontend/finance-assets/fullsize/URALSIB_color.svg", "name": "Уралсиб", "legalName": "ПАО «Банк Уралсиб»", "integration": "light", "inn": "0274062111"}, {"id": "bank-domrf", "enabled": true, "logo": "https://static.cdn-cian.ru/frontend/finance-assets/banks/logos/domrf.svg", "icon": "https://static.cdn-cian.ru/frontend/finance-assets/bages/domrf.svg", "fullsizeIcon": "https://static.cdn-cian.ru/frontend/finance-assets/fullsize/DOMRF_color.svg", "name": "Банк ДОМ.РФ", "legalName": "АО «Банк ДОМ.РФ", "integration": "light", "inn": "7725038124"}, {"id": "bank-domrf2", "enabled": true, "logo": "https://static.cdn-cian.ru/frontend/finance-assets/banks/logos/domrf.svg", "icon": "https://static.cdn-cian.ru/frontend/finance-assets/bages/domrf.svg", "fullsizeIcon": "https://static.cdn-cian.ru/frontend/finance-assets/fullsize/DOMRF_color.svg", "name": "Банк ДОМ.РФ Тест", "legalName": "АО «Банк ДОМ.РФ", "integration": "light", "env": ["ote"], "inn": "7725038124"}, {"id": "bank-t", "enabled": true, "logo": "https://static.cdn-cian.ru/frontend/finance-assets/banks/logos/tbank.svg", "icon": "https://static.cdn-cian.ru/frontend/finance-assets/bages/tbank.svg", "fullsizeIcon": "https://static.cdn-cian.ru/frontend/finance-assets/fullsize/TBANK_color.svg", "name": "Т-Банк", "legalName": "АО «ТБАНК»", "integration": "light", "inn": "7710140679"}, {"id": "bank-unicredit", "enabled": false, "logo": "https://static.cdn-cian.ru/frontend/finance-assets/banks/logos/unicredit.svg", "name": "ЮниКредит Банк", "integration": "none"}, {"id": "bank-mkb", "enabled": true, "logo": "https://static.cdn-cian.ru/frontend/finance-assets/banks/logos/mkb.svg", "icon": "https://static.cdn-cian.ru/frontend/finance-assets/bages/mkb.svg", "fullsizeIcon": "https://static.cdn-cian.ru/frontend/finance-assets/fullsize/MKB_color.svg", "name": "МКБ", "legalName": "ПАО «МКБ»", "integration": "light", "inn": "7734202860"}, {"id": "bank-personal-loan-emulator", "enabled": true, "logo": "https://static.cdn-cian.ru/frontend/finance-assets/banks/logos/bank-personal-loan-emulator.svg", "name": "Циан Банк", "integration": "api", "env": ["ote"]}, {"id": "bank-mts", "enabled": true, "logo": "https://static.cdn-cian.ru/frontend/finance-assets/banks/logos/mts.svg", "name": "МТС-Банк", "legalName": "ПАО «МТС-Банк»", "integration": "api", "env": ["ote"], "inn": "7702045051"}], "randomList": [{"id": "bank-alfa", "enabled": true, "logo": "https://static.cdn-cian.ru/frontend/finance-assets/banks/logos/alfa.svg", "icon": "https://static.cdn-cian.ru/frontend/finance-assets/bages/alfa.svg", "fullsizeIcon": "https://static.cdn-cian.ru/frontend/finance-assets/fullsize/ALFA_color.svg", "name": "Альфа-Банк", "legalName": "АО «Альфа-Банк»", "integration": "light", "inn": "7728168971"}, {"id": "bank-sovcom", "enabled": true, "logo": "https://static.cdn-cian.ru/frontend/finance-assets/banks/logos/sovcom.svg", "icon": "https://static.cdn-cian.ru/frontend/finance-assets/bages/sovkom-bank.svg", "fullsizeIcon": "https://static.cdn-cian.ru/frontend/finance-assets/fullsize/SOVKOMBANK_color.svg", "name": "Совкомбанк", "legalName": "ПАО «Совкомбанк»", "integration": "api", "inn": "4401116480"}, {"id": "bank-mkb", "enabled": true, "logo": "https://static.cdn-cian.ru/frontend/finance-assets/banks/logos/mkb.svg", "icon": "https://static.cdn-cian.ru/frontend/finance-assets/bages/mkb.svg", "fullsizeIcon": "https://static.cdn-cian.ru/frontend/finance-assets/fullsize/MKB_color.svg", "name": "МКБ", "legalName": "ПАО «МКБ»", "integration": "light", "inn": "7734202860"}, {"id": "bank-domrf", "enabled": true, "logo": "https://static.cdn-cian.ru/frontend/finance-assets/banks/logos/domrf.svg", "icon": "https://static.cdn-cian.ru/frontend/finance-assets/bages/domrf.svg", "fullsizeIcon": "https://static.cdn-cian.ru/frontend/finance-assets/fullsize/DOMRF_color.svg", "name": "Банк ДОМ.РФ", "legalName": "АО «Банк ДОМ.РФ", "integration": "light", "inn": "7725038124"}]}, "mortgagePromoDesign": null, "flatTourBooking": {"isTooltipOpen": false, "schedule": null}, "crossedOutPriceExcludeNewbuildingIds": [6190, 7904, 8753, 30342, 2096941, 1611, 34895], "comparisonNotification": null, "rs": {"buyAnalyticsFreeReportData": {"name": "БЦ Саммит. Москва, Тверская улица, 22.", "date": "от 13.04.2022", "url": "https://static.cdn-cian.ru/frontend/iap-statics-frontend/others/demo-analytics-report.pdf"}, "newbuildingBookingForm": {"enabled": false, "regions": [1, 4593, 2, 4588, 4777, 4897], "builders": [8079, 6399, 8114, 8110, 9164, 8136, 1301, 9591, 14557, 8130, 2351, 8113, 9037, 6381, 13100, 8077, 8160, 9034, 9079, 10109, 10814, 8131, 6399, 5747, 6381, 7042, 11623, 6008, 7046, 980, 7043, 11628, 8732, 6114, 15624, 9542, 17196, 15029, 7066, 8229, 7671, 15417, 8075, 17667, 8314, 14380, 9596, 15990, 18449, 14483, 18537, 10047, 9207, 8181, 8177, 17296, 13100, 10254, 10366, 10278, 10243, 18014, 9912, 14296, 10260, 15277, 15298, 15776, 17267, 14733, 10364, 15372, 18001, 14653, 18243, 10255, 10286, 6399, 14860, 980, 8602, 8624, 18773, 8664, 14375, 8665, 9817, 5747, 9164, 17534, 17605, 18729]}, "buyAnalyticsLegalDocsUrl": "https://www.cian.ru/legal-documents/dogovor_publichnaya_oferta_ob_okazanii_uslugi_analiticheskij_otchet_informacionno_analiticheskoj_platformy_iap_v_vydache_marketplejsa_326", "bestPlaceAnalyticsReportExampleUrl": "https://files.cian.ru/files/commercial/geo-analytics/report_example.pdf", "bestPlaceReportLegalDocsUrl": "https://www.cian.ru/legal-documents/dogovor_publichnaya_oferta_ob_okazanii_uslugi_otchet_o_privlekatelnosti_obekta_0", "bestPlaceReportBaseUrl": "https://cian.bestplace.pro/location-report", "bestPlaceReportProviderInfo": "Услугу предоставляет ООО «Бест-Плейс», ОГРН: 5167746245960"}, "isQaMode": false, "isRenterFormEnabled": true, "buyAnalyticsModal": {"isOpened": false, "reportPrice": 0, "property": null, "status": null, "paymentUrl": null, "transactionId": null, "userEmail": "", "isReportAvailable": false, "openReportAfterAuth": false}, "bestPlaceModal": {"isOpened": false}, "recommendedVillages": null, "genplan": null, "adfoxOffer": {"response": {"status": "ok", "data": {"offerType": "flat", "params": {"puid1": "deal_type_rent", "puid2": "offer_flat", "puid36": 1, "puid4": "offer_type_4", "puid5": "obl_id_1", "puid6": "251_500", "puid7": "2323", "puid8": 350000, "puid9": 120, "puid10": "no_agent", "puid16": "false", "puid17": "true", "puid18": 93, "puid19": "not_video"}, "dealType": "rent", "ymEvents": {"onPriceChange": null}}}, "statusCode": 200}, "isStartChatWidgetInDropdown": false, "rosreestr": null, "bestPlaceAnalytics": {"amount": null, "discount": null, "discountPrice": null, "paymentUrl": null, "status": null, "statusMessage": null, "userEmail": null}, "buildersProjectsLocations": [], "suburbanBuildersProjects": [], "reviewsGoToAppModal": {"isOpen": false}, "valuationTraps": {"isMyHomeObjectsExists": false}, "dailyrentBooking": {"general": {"isLoading": false, "price": "", "paymentSummary": null, "defaultBookingMessage": "", "error": ""}, "calendar": {"isOpen": false, "canBeBooked": true, "initialLoading": false, "daysAvailability": [], "showBookingCalendar": false, "dateInputText": "", "dates": {}}, "guests": {"isOpen": false, "guestsCount": 1, "minGuestsCount": 1, "maxGuestsCount": 99}}, "dailyrentActionType": null, "bannerRotation": 1, "comparison": {"comparison": {"props": [], "offers": [], "notFoundUrl": "/kupit-kvartiru/", "seoData": {"h1": "Сравнение квартир", "title": "Сравнение квартир в Москве - ЦИАН", "description": "Сравнение квартир в Москве по цене, площади и другим параметрам. Выбирайте на ЦИАН."}}}, "chatOnboarding": {"wasChatOpened": false}}