{"abGroup": 0, "abUseExperiments": [{"experimentName": "aud_desktop_bx495_expert_opinion_gpt_newb", "groupName": null}, {"experimentName": "aud_desktop_bx664_chats_from_object_card", "groupName": "B"}, {"experimentName": "b2b_pa16510_replacement_mortgage_banner_on_adcard_with_cpd_web", "groupName": null}, {"experimentName": "newbuilding_buzzoola_integration_test_web", "groupName": "Adfox"}, {"experimentName": "newbuilding_flatsale_trap_desktop", "groupName": "A"}, {"experimentName": "newbuilding_kpn_chats_card_desktop", "groupName": null}, {"experimentName": "newbuilding_rent_trap_desktop", "groupName": "C"}, {"experimentName": "newbuilding_suburban_trap_desktop", "groupName": "A"}, {"experimentName": "newbuilding_trust_safety_desktop", "groupName": "enabled"}], "aside": {"height": 0, "isNavigationActive": false, "activeAnchor": "#photos", "isCompactModeEnabled": false}, "hideOffer": {}, "bookedOfferId": 0, "captchaSiteKey": "6LfvfCETAAAAABxHQ2wxiTT_mILt0c87axZn7zOU", "captchaSpamSiteKey": "6LdpqSQUAAAAAJXo9mQJY2QYw2rSi2D0-ZXctcw_", "commentsData": {"commentText": "", "editing": false, "isOpen": false, "messageError": "", "statusFetch": "none", "openAfterAuth": false}, "favoriteMotivation": {"isActive": true, "isShows": false}, "feedback": {"isComplaintPopupOpened": false, "isFeedbackSent": false, "isFeedbackSentPopupOpened": false, "isFormPopupOpened": false, "isPopupOpened": false, "status": "Initial"}, "gallery": {}, "legend": {"isOpen": false}, "mapSimilar": null, "mapTabs": {"activeTab": "similarOffers"}, "mortgage": {"rates": {"flat": {"used": 17.9, "new": 5.7}, "appartments": {"used": 19, "new": 20.7}, "suburban": {"new": 6, "used": 21.1}}, "bankIds": ["bank-alfa", "bank-domrf", "bank-mkb", "bank-psb", "bank-sovcom", "bank-t", "bank-uralsib", "bank-vtb-new"]}, "mortgageGallery": {}, "newbuildingBookedFromDeveloper": {"isConfirmOpen": false, "status": "initial"}, "offerChat": {"requestStatus": "initial", "isChatsEnabled": false, "isChatOpened": false, "openAfterAuth": false, "isOnline": false, "hintQuestions": []}, "consultantCianChat": {"requestStatus": "initial", "chatId": null, "isLoading": false, "isError": false, "isErrorPopupOpened": false, "isEnabled": false, "isOpened": false, "isAutorisationPopupOpened": false}, "offerData": {"offer": {"category": "flatRent", "status": "published", "dealType": "rent", "offerType": "flat", "geo": {"address": [{"fullName": "Москва", "id": 1, "locationTypeId": 1, "name": "Москва", "shortName": "Москва", "type": "location", "url": "https://www.cian.ru/snyat-1-komnatnuyu-kvartiru/"}, {"fullName": "СЗАО", "id": 1, "locationTypeId": -1, "name": "СЗАО", "shortName": "СЗАО", "type": "okrug", "url": "https://www.cian.ru/snyat-1-komnatnuyu-kvartiru-moskva-szao-041/"}, {"fullName": "район Хорошево-Мневники", "id": 130, "locationTypeId": -1, "name": "Хорошево-Мневники", "shortName": "р-н Хорошево-Мневники", "type": "raion", "url": "https://www.cian.ru/snyat-1-komnatnuyu-kvartiru-moskva-horoshevo-mnevniki-04130/"}, {"fullName": "Шелепихинская набережная", "id": 2443, "locationTypeId": -1, "name": "Шелепихинская", "shortName": "Шелепихинская наб.", "type": "street", "url": "https://www.cian.ru/snyat-1-komnatnuyu-kvartiru-moskva-shelepihinskaya-naberezhnaya-022443/"}, {"fullName": "34к3зд7", "id": 10288868, "locationTypeId": -1, "name": "34к3зд7", "shortName": "34к3зд7", "type": "house", "url": "https://www.cian.ru/cat.php?deal_type=rent&engine_version=2&house%5B0%5D=10288868&offer_type=flat&room1=1&type=4"}], "coordinates": {"lat": 55.763214, "lng": 37.515191}, "highways": [], "railways": [{"id": 707, "directionIds": [11], "distance": "1.0", "time": 21, "name": "Тестовская", "travelType": "byFoot"}, {"id": 708, "directionIds": [11], "distance": "3.0", "time": 5, "name": "Фили", "travelType": "byCar"}, {"id": 708, "directionIds": [11], "distance": "3.0", "time": 42, "name": "Фили", "travelType": "byFoot"}, {"id": 699, "directionIds": [11], "distance": "3.0", "time": 44, "name": "Беговая", "travelType": "byFoot"}, {"id": 707, "directionIds": [11], "distance": "4.0", "time": 7, "name": "Тестовская", "travelType": "byCar"}, {"id": 699, "directionIds": [11], "distance": "4.0", "time": 6, "name": "Беговая", "travelType": "byCar"}], "undergrounds": [{"id": 311, "name": "Шелепиха", "lineColor": "FA6F9E", "travelType": "walk", "travelTime": 14, "url": "https://www.cian.ru/snyat-1-komnatnuyu-kvartiru-moskva-stanciya-mck-shelepiha/", "underConstruction": false, "lineType": "mck"}, {"id": 453, "name": "Шелепиха", "lineColor": "7ACDCE", "travelType": "walk", "travelTime": 11, "url": "https://www.cian.ru/snyat-1-komnatnuyu-kvartiru-moskva-metro-shelepiha/", "underConstruction": false}, {"id": 512, "name": "Москва-Сити", "lineColor": "40B280", "travelType": "walk", "travelTime": 23, "url": "https://www.cian.ru/snyat-1-komnatnuyu-kvartiru-moskva-metro-moskva-siti/", "underConstruction": false, "lineType": "mcd4"}]}, "id": 322052883, "objectGuid": "38b2cd70-1805-4f72-8a1e-255e35e9e15f", "cianId": 322052883, "userId": 6741627, "publishedUserId": 6741627, "cianUserId": 14228, "isByHomeowner": false, "description": "Предлагаем шикарную, просторную квартиру в долгосрочную аренду. Выполнен дорогостоящий ремонт из качественных материалов, в квартире никто не жил, все абсолютно новое. Квартира обладает красивыми видовыми характеристиками и всей необходимой для комфортного проживания мебелью и техникой. В стоимость включено машино место на подземном паркинге, лифт ведет сразу в подьед. К проживанию рассматривают строго одного человека либо семейную пару, , без питомцев и детей.\n-----\nПримечание: у собственника могут быть дополнительные пожелания к жильцам - обсудите их в чате или по телефону", "photos": [{"id": 2636607996, "isDefault": true, "fullUrl": "https://images.cdn-cian.ru/images/kvartira-moskva-shelepihinskaya-naberezhnaya-2636607996-1.jpg", "thumbnailUrl": "https://images.cdn-cian.ru/images/kvartira-moskva-shelepihinskaya-naberezhnaya-2636607996-2.jpg", "thumbnail2Url": "https://images.cdn-cian.ru/images/kvartira-moskva-shelepihinskaya-naberezhnaya-2636607996-4.jpg", "miniUrl": "https://images.cdn-cian.ru/images/kvartira-moskva-shelepihinskaya-naberezhnaya-2636607996-3.jpg", "isCianLayout": false}, {"id": 2636607994, "isDefault": false, "fullUrl": "https://images.cdn-cian.ru/images/kvartira-moskva-shelepihinskaya-naberezhnaya-2636607994-1.jpg", "thumbnailUrl": "https://images.cdn-cian.ru/images/kvartira-moskva-shelepihinskaya-naberezhnaya-2636607994-2.jpg", "thumbnail2Url": "https://images.cdn-cian.ru/images/kvartira-moskva-shelepihinskaya-naberezhnaya-2636607994-4.jpg", "miniUrl": "https://images.cdn-cian.ru/images/kvartira-moskva-shelepihinskaya-naberezhnaya-2636607994-3.jpg", "isCianLayout": false}, {"id": 2636607986, "isDefault": false, "fullUrl": "https://images.cdn-cian.ru/images/kvartira-moskva-shelepihinskaya-naberezhnaya-2636607986-1.jpg", "thumbnailUrl": "https://images.cdn-cian.ru/images/kvartira-moskva-shelepihinskaya-naberezhnaya-2636607986-2.jpg", "thumbnail2Url": "https://images.cdn-cian.ru/images/kvartira-moskva-shelepihinskaya-naberezhnaya-2636607986-4.jpg", "miniUrl": "https://images.cdn-cian.ru/images/kvartira-moskva-shelepihinskaya-naberezhnaya-2636607986-3.jpg", "isCianLayout": false}, {"id": 2636630665, "isDefault": false, "fullUrl": "https://images.cdn-cian.ru/images/kvartira-moskva-shelepihinskaya-naberezhnaya-2636630665-1.jpg", "thumbnailUrl": "https://images.cdn-cian.ru/images/kvartira-moskva-shelepihinskaya-naberezhnaya-2636630665-2.jpg", "thumbnail2Url": "https://images.cdn-cian.ru/images/kvartira-moskva-shelepihinskaya-naberezhnaya-2636630665-4.jpg", "miniUrl": "https://images.cdn-cian.ru/images/kvartira-moskva-shelepihinskaya-naberezhnaya-2636630665-3.jpg", "isCianLayout": false}, {"id": 2636608000, "isDefault": false, "fullUrl": "https://images.cdn-cian.ru/images/kvartira-moskva-shelepihinskaya-naberezhnaya-2636608000-1.jpg", "thumbnailUrl": "https://images.cdn-cian.ru/images/kvartira-moskva-shelepihinskaya-naberezhnaya-2636608000-2.jpg", "thumbnail2Url": "https://images.cdn-cian.ru/images/kvartira-moskva-shelepihinskaya-naberezhnaya-2636608000-4.jpg", "miniUrl": "https://images.cdn-cian.ru/images/kvartira-moskva-shelepihinskaya-naberezhnaya-2636608000-3.jpg", "isCianLayout": false}, {"id": 2636625004, "isDefault": false, "fullUrl": "https://images.cdn-cian.ru/images/kvartira-moskva-shelepihinskaya-naberezhnaya-2636625004-1.jpg", "thumbnailUrl": "https://images.cdn-cian.ru/images/kvartira-moskva-shelepihinskaya-naberezhnaya-2636625004-2.jpg", "thumbnail2Url": "https://images.cdn-cian.ru/images/kvartira-moskva-shelepihinskaya-naberezhnaya-2636625004-4.jpg", "miniUrl": "https://images.cdn-cian.ru/images/kvartira-moskva-shelepihinskaya-naberezhnaya-2636625004-3.jpg", "isCianLayout": false}, {"id": 2636607998, "isDefault": false, "fullUrl": "https://images.cdn-cian.ru/images/kvartira-moskva-shelepihinskaya-naberezhnaya-2636607998-1.jpg", "thumbnailUrl": "https://images.cdn-cian.ru/images/kvartira-moskva-shelepihinskaya-naberezhnaya-2636607998-2.jpg", "thumbnail2Url": "https://images.cdn-cian.ru/images/kvartira-moskva-shelepihinskaya-naberezhnaya-2636607998-4.jpg", "miniUrl": "https://images.cdn-cian.ru/images/kvartira-moskva-shelepihinskaya-naberezhnaya-2636607998-3.jpg", "isCianLayout": false}, {"id": 2636607958, "isDefault": false, "fullUrl": "https://images.cdn-cian.ru/images/kvartira-moskva-shelepihinskaya-naberezhnaya-2636607958-1.jpg", "thumbnailUrl": "https://images.cdn-cian.ru/images/kvartira-moskva-shelepihinskaya-naberezhnaya-2636607958-2.jpg", "thumbnail2Url": "https://images.cdn-cian.ru/images/kvartira-moskva-shelepihinskaya-naberezhnaya-2636607958-4.jpg", "miniUrl": "https://images.cdn-cian.ru/images/kvartira-moskva-shelepihinskaya-naberezhnaya-2636607958-3.jpg", "isCianLayout": false}, {"id": 2636607984, "isDefault": false, "fullUrl": "https://images.cdn-cian.ru/images/kvartira-moskva-shelepihinskaya-naberezhnaya-2636607984-1.jpg", "thumbnailUrl": "https://images.cdn-cian.ru/images/kvartira-moskva-shelepihinskaya-naberezhnaya-2636607984-2.jpg", "thumbnail2Url": "https://images.cdn-cian.ru/images/kvartira-moskva-shelepihinskaya-naberezhnaya-2636607984-4.jpg", "miniUrl": "https://images.cdn-cian.ru/images/kvartira-moskva-shelepihinskaya-naberezhnaya-2636607984-3.jpg", "isCianLayout": false}, {"id": 2636607983, "isDefault": false, "fullUrl": "https://images.cdn-cian.ru/images/kvartira-moskva-shelepihinskaya-naberezhnaya-2636607983-1.jpg", "thumbnailUrl": "https://images.cdn-cian.ru/images/kvartira-moskva-shelepihinskaya-naberezhnaya-2636607983-2.jpg", "thumbnail2Url": "https://images.cdn-cian.ru/images/kvartira-moskva-shelepihinskaya-naberezhnaya-2636607983-4.jpg", "miniUrl": "https://images.cdn-cian.ru/images/kvartira-moskva-shelepihinskaya-naberezhnaya-2636607983-3.jpg", "isCianLayout": false}, {"id": 2636607988, "isDefault": false, "fullUrl": "https://images.cdn-cian.ru/images/kvartira-moskva-shelepihinskaya-naberezhnaya-2636607988-1.jpg", "thumbnailUrl": "https://images.cdn-cian.ru/images/kvartira-moskva-shelepihinskaya-naberezhnaya-2636607988-2.jpg", "thumbnail2Url": "https://images.cdn-cian.ru/images/kvartira-moskva-shelepihinskaya-naberezhnaya-2636607988-4.jpg", "miniUrl": "https://images.cdn-cian.ru/images/kvartira-moskva-shelepihinskaya-naberezhnaya-2636607988-3.jpg", "isCianLayout": false}, {"id": 2636607970, "isDefault": false, "fullUrl": "https://images.cdn-cian.ru/images/kvartira-moskva-shelepihinskaya-naberezhnaya-2636607970-1.jpg", "thumbnailUrl": "https://images.cdn-cian.ru/images/kvartira-moskva-shelepihinskaya-naberezhnaya-2636607970-2.jpg", "thumbnail2Url": "https://images.cdn-cian.ru/images/kvartira-moskva-shelepihinskaya-naberezhnaya-2636607970-4.jpg", "miniUrl": "https://images.cdn-cian.ru/images/kvartira-moskva-shelepihinskaya-naberezhnaya-2636607970-3.jpg", "isCianLayout": false}, {"id": 2636608002, "isDefault": false, "fullUrl": "https://images.cdn-cian.ru/images/kvartira-moskva-shelepihinskaya-naberezhnaya-2636608002-1.jpg", "thumbnailUrl": "https://images.cdn-cian.ru/images/kvartira-moskva-shelepihinskaya-naberezhnaya-2636608002-2.jpg", "thumbnail2Url": "https://images.cdn-cian.ru/images/kvartira-moskva-shelepihinskaya-naberezhnaya-2636608002-4.jpg", "miniUrl": "https://images.cdn-cian.ru/images/kvartira-moskva-shelepihinskaya-naberezhnaya-2636608002-3.jpg", "isCianLayout": false}, {"id": 2636608008, "isDefault": false, "fullUrl": "https://images.cdn-cian.ru/images/kvartira-moskva-shelepihinskaya-naberezhnaya-2636608008-1.jpg", "thumbnailUrl": "https://images.cdn-cian.ru/images/kvartira-moskva-shelepihinskaya-naberezhnaya-2636608008-2.jpg", "thumbnail2Url": "https://images.cdn-cian.ru/images/kvartira-moskva-shelepihinskaya-naberezhnaya-2636608008-4.jpg", "miniUrl": "https://images.cdn-cian.ru/images/kvartira-moskva-shelepihinskaya-naberezhnaya-2636608008-3.jpg", "isCianLayout": false}, {"id": 2636630666, "isDefault": false, "fullUrl": "https://images.cdn-cian.ru/images/kvartira-moskva-shelepihinskaya-naberezhnaya-2636630666-1.jpg", "thumbnailUrl": "https://images.cdn-cian.ru/images/kvartira-moskva-shelepihinskaya-naberezhnaya-2636630666-2.jpg", "thumbnail2Url": "https://images.cdn-cian.ru/images/kvartira-moskva-shelepihinskaya-naberezhnaya-2636630666-4.jpg", "miniUrl": "https://images.cdn-cian.ru/images/kvartira-moskva-shelepihinskaya-naberezhnaya-2636630666-3.jpg", "isCianLayout": false}, {"id": 2636630660, "isDefault": false, "fullUrl": "https://images.cdn-cian.ru/images/kvartira-moskva-shelepihinskaya-naberezhnaya-2636630660-1.jpg", "thumbnailUrl": "https://images.cdn-cian.ru/images/kvartira-moskva-shelepihinskaya-naberezhnaya-2636630660-2.jpg", "thumbnail2Url": "https://images.cdn-cian.ru/images/kvartira-moskva-shelepihinskaya-naberezhnaya-2636630660-4.jpg", "miniUrl": "https://images.cdn-cian.ru/images/kvartira-moskva-shelepihinskaya-naberezhnaya-2636630660-3.jpg", "isCianLayout": false}, {"id": 2636630668, "isDefault": false, "fullUrl": "https://images.cdn-cian.ru/images/kvartira-moskva-shelepihinskaya-naberezhnaya-2636630668-1.jpg", "thumbnailUrl": "https://images.cdn-cian.ru/images/kvartira-moskva-shelepihinskaya-naberezhnaya-2636630668-2.jpg", "thumbnail2Url": "https://images.cdn-cian.ru/images/kvartira-moskva-shelepihinskaya-naberezhnaya-2636630668-4.jpg", "miniUrl": "https://images.cdn-cian.ru/images/kvartira-moskva-shelepihinskaya-naberezhnaya-2636630668-3.jpg", "isCianLayout": false}, {"id": 2636608010, "isDefault": false, "fullUrl": "https://images.cdn-cian.ru/images/kvartira-moskva-shelepihinskaya-naberezhnaya-2636608010-1.jpg", "thumbnailUrl": "https://images.cdn-cian.ru/images/kvartira-moskva-shelepihinskaya-naberezhnaya-2636608010-2.jpg", "thumbnail2Url": "https://images.cdn-cian.ru/images/kvartira-moskva-shelepihinskaya-naberezhnaya-2636608010-4.jpg", "miniUrl": "https://images.cdn-cian.ru/images/kvartira-moskva-shelepihinskaya-naberezhnaya-2636608010-3.jpg", "isCianLayout": false}, {"id": 2636630659, "isDefault": false, "fullUrl": "https://images.cdn-cian.ru/images/kvartira-moskva-shelepihinskaya-naberezhnaya-2636630659-1.jpg", "thumbnailUrl": "https://images.cdn-cian.ru/images/kvartira-moskva-shelepihinskaya-naberezhnaya-2636630659-2.jpg", "thumbnail2Url": "https://images.cdn-cian.ru/images/kvartira-moskva-shelepihinskaya-naberezhnaya-2636630659-4.jpg", "miniUrl": "https://images.cdn-cian.ru/images/kvartira-moskva-shelepihinskaya-naberezhnaya-2636630659-3.jpg", "isCianLayout": false}, {"id": 2636630650, "isDefault": false, "fullUrl": "https://images.cdn-cian.ru/images/kvartira-moskva-shelepihinskaya-naberezhnaya-2636630650-1.jpg", "thumbnailUrl": "https://images.cdn-cian.ru/images/kvartira-moskva-shelepihinskaya-naberezhnaya-2636630650-2.jpg", "thumbnail2Url": "https://images.cdn-cian.ru/images/kvartira-moskva-shelepihinskaya-naberezhnaya-2636630650-4.jpg", "miniUrl": "https://images.cdn-cian.ru/images/kvartira-moskva-shelepihinskaya-naberezhnaya-2636630650-3.jpg", "isCianLayout": false}, {"id": 2636608006, "isDefault": false, "fullUrl": "https://images.cdn-cian.ru/images/kvartira-moskva-shelepihinskaya-naberezhnaya-2636608006-1.jpg", "thumbnailUrl": "https://images.cdn-cian.ru/images/kvartira-moskva-shelepihinskaya-naberezhnaya-2636608006-2.jpg", "thumbnail2Url": "https://images.cdn-cian.ru/images/kvartira-moskva-shelepihinskaya-naberezhnaya-2636608006-4.jpg", "miniUrl": "https://images.cdn-cian.ru/images/kvartira-moskva-shelepihinskaya-naberezhnaya-2636608006-3.jpg", "isCianLayout": false}], "phones": [{"countryCode": "+7", "number": "9858327697"}], "publishTerms": {"terms": [{"services": ["paid"], "days": 30, "type": "periodical", "tariffIdentificator": {"tariffId": 1005401, "tariffGridType": "packageTariff"}}], "autoprolong": false}, "flatType": "rooms", "roomType": "separate", "isApartments": false, "totalArea": "43.0", "kitchenArea": "12.0", "loggiasCount": 0, "balconiesCount": 0, "windowsViewType": "yard", "separateWcsCount": 0, "combinedWcsCount": 1, "repairType": "euro", "hasPhone": false, "hasFridge": true, "hasDishwasher": true, "hasWasher": true, "hasFurniture": true, "hasKitchenFurniture": true, "hasConditioner": true, "hasTv": true, "hasInternet": true, "hasBathtub": false, "hasShower": true, "flags": {"isArchived": false, "isCommercialOwnershipVerified": false}, "hasLift": true, "specialty": {"types": [], "additionalTypes": []}, "isNeedHideExactAddress": false, "areaParts": [], "roomsCount": 1, "floorNumber": 16, "bargainTerms": {"price": 150000, "priceType": "all", "currency": "rur", "paymentPeriod": "monthly", "leaseTermType": "longTerm", "prepayMonths": 1, "deposit": 150000, "utilitiesTerms": {"includedInPrice": true, "price": 0, "flowMetersNotIncludedInPrice": true}, "includedOptions": [], "clientFee": 0, "agentFee": 0, "prices": {"rur": 150000, "usd": 1848, "eur": 1595}, "depositPrices": {"rur": 150000, "usd": 1848, "eur": 1595}, "utilitiesTermsPrices": {"rur": 0, "usd": 0, "eur": 0}, "tags": []}, "building": {"floorsCount": 24, "parking": {"type": "underground"}, "ceilingHeight": "3.2", "totalArea": "43.0", "liftTypes": [], "cranageTypes": [], "passengerLiftsCount": 2, "cargoLiftsCount": 2}, "editDate": "2025-10-07T11:43:33.213000+00:00", "humanizedEditDate": "7 окт, 11:43", "isInHiddenBase": false, "isObjectHidden": false, "isClosedVisibility": false, "videos": [], "exportLinks": {"pdfUrl": "/export/pdf/rent/flat/322052883/", "docxUrl": "/export/docx/rent/flat/322052883/"}, "passengerLiftsCount": 2, "cargoLiftsCount": 2, "added": "7 окт, 11:43", "valueAddedServices": {"isStandard": false, "isTop3": false, "isPremium": false}, "categoriesIds": [1000, 1100, 1110, 1111], "publicationDate": 1758361786, "creationDate": "2025-09-20T12:49:46.313", "recoveryLink": "/razmestit-obyavlenie/322052883/", "trackingData": {"moId": 0, "oblId": 1, "cityId": 1, "fbRegion": "Москва", "fbCity": "Москва"}, "editPhoto": "/realty/add2.aspx?id=322052883", "newEdit": "/razmestit-obyavlenie/?realty_id=322052883", "certificate": "https://www.cian.ru/newobjects/cian/certification/get?announcementId=322052883", "edit": "/realty/add1.aspx?id=322052883", "similarOffersLink": "", "similarOffersCount": 0, "buildersIds": [], "isImported": false, "userConfirmedFix": false, "timezone": 3, "isEnabledCallTracking": true, "callTrackingProvider": "mts", "isRentByParts": false, "isDuplicate": false, "userTrust": "notInvolved", "userTrustLevel": "notInvolved", "showWarningMessage": false, "moderationInfo": {"showContactWarningMessage": false}, "isUnique": true, "isUniqueCheckDate": "2025-10-11", "isCianPartner": false, "isIllegalConstruction": false, "amenities": [], "externalOfferUrl": "", "cianLayouts": null, "newbuilding": {"id": 0, "isFromBuilder": false, "isFromDeveloper": false, "isFromLeadFactory": false, "isFromSeller": false, "isReliable": false, "isTariffPremium": false, "isPremium": false, "name": "", "newbuildingFeatures": null, "showJkReliableFlag": false}, "demolishedInMoscowProgramm": false}, "seoLinks": [], "breadcrumbs": [{"url": "https://www.cian.ru/", "title": "Недвижимость в Москве"}, {"url": "https://www.cian.ru/snyat/", "title": "Аренда"}, {"url": "https://www.cian.ru/snyat-1-komnatnuyu-kvartiru/", "title": "Аренда 1-комнатных квартир в Москве"}, {"url": "https://www.cian.ru/snyat-1-komnatnuyu-kvartiru-moskva-szao-041/", "title": "СЗАО"}, {"url": "https://www.cian.ru/snyat-1-komnatnuyu-kvartiru-moskva-horoshevo-mnevniki-04130/", "title": "Хорошево-Мневники"}, {"url": "https://www.cian.ru/snyat-1-komnatnuyu-kvartiru-moskva-stanciya-mck-shelepiha/", "title": "метро Шелепиха"}, {"url": "https://www.cian.ru/snyat-1-komnatnuyu-kvartiru-moskva-shelepihinskaya-naberezhnaya-022443/", "title": "Шелепихинская набережная"}], "similarOffersMapQs": "engine_version=2&deal_type=rent&offer_type=flat&region=1&minprice=127500&maxprice=172500&room1=1&room2=1&type=4", "similarNewObjects": [], "linkToMap": "https://www.cian.ru/map/?engine_version=2&deal_type=rent&offer_type=flat&region=1&minprice=127500&maxprice=172500&room1=1&room2=1&type=4&zoom=16&center=55.763214%2C37.515191", "isFavorite": false, "offerFoldersCount": 0, "subscription": {"isSubscribed": false}, "priceChanges": [{"changeTime": "2025-09-20T09:49:47.915823+00:00", "priceData": {"currency": "rur", "price": 150000, "paymentPeriod": "monthly"}}], "offences": [], "stats": {"daily": 2, "total": 89, "totalViewsFormattedString": "89 просмотров, 2 за сегодня", "totalUniqueViewsFormattedString": "52 уникальных"}, "notes": {}, "agent": {"id": 14228, "cianUserId": 14228, "realtyUserId": 6741627, "accountType": "specialist", "creationDate": "2007-06-13T15:50:21+00:00", "isPro": true, "phones": [{"confirmed": true}, {"confirmed": true}], "skills": [], "isDeveloper": false, "isRecidivist": false, "isUserOffersHasErrors": false, "offersCount": 8, "offersLink": "https://www.cian.ru/agents/14228/", "availableServices": {"isUploadsAvailable": true, "isCallTrackingAvailable": false, "isPhoneChangingAvailable": false, "isServicePackagesAvailable": true, "canUseHiddenBase": true}, "userType": "realtor_based", "removeCompetitor": false, "status": "hidden", "isSubAgent": false, "isMessagingEnabled": false, "isPassportVerified": false, "isSelfEmployed": false, "isPrivateBroker": true, "isCianPartner": false, "canShowOnline": false, "moderationInfo": {"qualityLevelInfo": {"levelSystemName": "high", "levelName": "Высокий уровень", "levelOrder": 3, "hasVerifiedDocuments": false, "highResponsibility": true, "isSuperAgent": false, "isSuperHost": false, "isBlocked": false, "showSuperHost": false, "showSuperAgent": false, "showHighResponsibility": true}, "isUserIdentified": false, "isUserIdentifiedByDocuments": false, "showUserIdentifiedByDocuments": false}, "isHidden": false, "agentLists": []}, "user": {"isAuthenticated": false, "permissions": {"canModerateUsers": false, "canModerateAnnouncements": false, "canModerateAnnouncementsExpert": false, "canViewUsers": false, "canViewAnnouncements": false}, "ga": {"type": "", "balance": 0, "packages": [], "emailMd5": ""}}, "agentAvailability": {"userId": 6741627, "available": false, "message": "Напишите ему или позвоните завтра.", "title": "Специалист работает с 10:00 по 22:00.", "availableFrom": "2025-10-13T10:00:00+03:00", "availableTo": "2025-10-13T22:00:00+03:00"}, "agentReviews": {"approvedReviewsCount": 0, "entityName": "", "isNotificationDisabled": true, "isUserMobilePushSubscribed": false, "isUserSubscribed": false, "rateCounts": [{"count": 0, "rate": 5}, {"count": 0, "rate": 4}, {"count": 0, "rate": 3}, {"count": 0, "rate": 2}, {"count": 0, "rate": 1}], "reviews": [], "subscriptionEmail": "", "totalCount": 0}, "isHiddenByUser": false, "degradationInfo": {}, "newbuildingsNearby": {"title": "Своя квартира в новостройке поблизости", "text": "Успейте купить квартиру с выгодными ставками по ипотеке", "newbuildings": [{"imageUrl": "https://images.cdn-cian.ru/images/level-prichalnyy-moskva-jk-2422265471-7.jpg", "url": "https://zhk-level-prichalnyy-i.cian.ru/", "name": "ЖК «Level Причальный (Левел Причальный)»", "minPrice": "от 69 638 ₽/мес", "underground": {"name": "Шелепиха", "lineColor": "FA6F9E"}, "highway": {"name": "Рублевское"}, "analytics": {"id": 1529615, "position": 1, "type": "JK"}}, {"imageUrl": "https://images.cdn-cian.ru/images/beregovoy2-moskva-jk-2541379223-7.jpg", "url": "https://zhk-beregovoy-2-i.cian.ru/", "name": "ЖК «Береговой-2»", "minPrice": "от 122 434 ₽/мес", "underground": {"name": "Звенигородская", "lineColor": "27303F"}, "analytics": {"id": 46840, "position": 2, "type": "JK"}}, {"imageUrl": "https://images.cdn-cian.ru/images/emotion-moskva-jk-2414634124-7.jpg", "url": "https://zhk-emotion-i.cian.ru/", "name": "ЖК «Emotion (Эмоушен)»", "minPrice": "от 62 029 ₽/мес", "underground": {"name": "Полежаевская", "lineColor": "94007C"}, "analytics": {"id": 4417906, "position": 3, "type": "JK"}}, {"imageUrl": "https://images.cdn-cian.ru/images/sydney-city-moskva-jk-2111596072-7.jpg", "url": "https://zhk-sydney-city-i.cian.ru/", "name": "ЖК «Sydney City (Сидней Сити)»", "minPrice": "от 85 496 ₽/мес", "underground": {"name": "Хорошёво", "lineColor": "FA6F9E"}, "analytics": {"id": 2446053, "position": 4, "type": "JK"}}], "buttonLink": "https://www.cian.ru/map/?engine_version=2&deal_type=sale&offer_type=flat&object_type%5B0%5D=2&zoom=12&center=55.763214%2C37.515191", "buttonText": "Смотреть все предложения"}, "rosreestrInfoV2": {"showCheckedLabel": false}, "isOnlineRegistrationAvailable": false, "factoids": [{"title": "Общая площадь", "icon": "https://images.cdn-cian.ru/imgmobile/icons/offer_card/size.svg", "value": "43 м²"}, {"title": "Площадь кухни", "icon": "https://images.cdn-cian.ru/imgmobile/icons/offer_card/kitchen.svg", "value": "12 м²"}, {"title": "Этаж", "icon": "https://images.cdn-cian.ru/imgmobile/icons/offer_card/floor.svg", "value": "16 из 24"}], "sidebar": [{"title": "Оплата ЖКХ", "value": "включена (без счётчиков)"}, {"title": "Залог", "value": "150 000 ₽"}, {"title": "Комиссии", "value": "нет"}, {"title": "Предоплата", "value": "1 месяц"}, {"title": "Срок аренды", "value": "от года"}], "features": [{"title": "О квартире", "id": "aboutFlat", "features": [{"value": "43 м²", "label": "Общая площадь"}, {"value": "12 м²", "label": "Площадь кухни"}, {"value": "3,2 м", "label": "Высота потолков"}, {"value": "Изолированная", "label": "Планировка"}, {"value": "1 совмещенный", "label": "Санузел"}, {"value": "Во двор", "label": "Вид из окон"}, {"value": "Евроремонт", "label": "Ремонт"}]}, {"title": "О доме", "id": "aboutBuilding", "features": [{"value": "2 пассажирских, 2 грузовых", "label": "Количество лифтов"}, {"value": "Подземная", "label": "Парковка"}]}], "seoData": {"socialNetworksTitle": {"full": "Сдаётся, 1-комнатная квартира, за 150 000 ₽/мес., 43.0 м², этаж 16/24", "short": "Сдаётся, 1-комн. кв., за 150 000 ₽/мес."}, "mainTitle": "Снять однокомнатную квартиру 43.0м² Шелепихинская наб., 34к3зд7, Москва, СЗАО, р-н Хорошево-Мневники м. Шелепиха - база ЦИАН, объявление 322052883", "description": "➜ Арендуйте однокомнатную квартиру площадью 43.0м² Шелепихинская наб., 34к3зд7, Москва, СЗАО, р-н Хорошево-Мневники м. Шелепиха. Цена аренды - 150 000 руб. в месяц. Недвижимость на ЦИАН - объявление 322052883", "micromarking": {"@context": "https://schema.org/", "@type": "Product", "name": "", "image": ["https://images.cdn-cian.ru/images/kvartira-moskva-shelepihinskaya-naberezhnaya-2636607996-1.jpg", "https://images.cdn-cian.ru/images/kvartira-moskva-shelepihinskaya-naberezhnaya-2636607994-1.jpg", "https://images.cdn-cian.ru/images/kvartira-moskva-shelepihinskaya-naberezhnaya-2636607986-1.jpg", "https://images.cdn-cian.ru/images/kvartira-moskva-shelepihinskaya-naberezhnaya-2636630665-1.jpg", "https://images.cdn-cian.ru/images/kvartira-moskva-shelepihinskaya-naberezhnaya-2636608000-1.jpg", "https://images.cdn-cian.ru/images/kvartira-moskva-shelepihinskaya-naberezhnaya-2636625004-1.jpg", "https://images.cdn-cian.ru/images/kvartira-moskva-shelepihinskaya-naberezhnaya-2636607998-1.jpg", "https://images.cdn-cian.ru/images/kvartira-moskva-shelepihinskaya-naberezhnaya-2636607958-1.jpg", "https://images.cdn-cian.ru/images/kvartira-moskva-shelepihinskaya-naberezhnaya-2636607984-1.jpg", "https://images.cdn-cian.ru/images/kvartira-moskva-shelepihinskaya-naberezhnaya-2636607983-1.jpg", "https://images.cdn-cian.ru/images/kvartira-moskva-shelepihinskaya-naberezhnaya-2636607988-1.jpg", "https://images.cdn-cian.ru/images/kvartira-moskva-shelepihinskaya-naberezhnaya-2636607970-1.jpg", "https://images.cdn-cian.ru/images/kvartira-moskva-shelepihinskaya-naberezhnaya-2636608002-1.jpg", "https://images.cdn-cian.ru/images/kvartira-moskva-shelepihinskaya-naberezhnaya-2636608008-1.jpg", "https://images.cdn-cian.ru/images/kvartira-moskva-shelepihinskaya-naberezhnaya-2636630666-1.jpg", "https://images.cdn-cian.ru/images/kvartira-moskva-shelepihinskaya-naberezhnaya-2636630660-1.jpg", "https://images.cdn-cian.ru/images/kvartira-moskva-shelepihinskaya-naberezhnaya-2636630668-1.jpg", "https://images.cdn-cian.ru/images/kvartira-moskva-shelepihinskaya-naberezhnaya-2636608010-1.jpg", "https://images.cdn-cian.ru/images/kvartira-moskva-shelepihinskaya-naberezhnaya-2636630659-1.jpg", "https://images.cdn-cian.ru/images/kvartira-moskva-shelepihinskaya-naberezhnaya-2636630650-1.jpg", "https://images.cdn-cian.ru/images/kvartira-moskva-shelepihinskaya-naberezhnaya-2636608006-1.jpg"], "description": "Предлагаем шикарную, просторную квартиру в долгосрочную аренду. Выполнен дорогостоящий ремонт из качественных материалов, в квартире никто не жил, все абсолютно новое. Квартира обладает красивыми видовыми характеристиками и всей необходимой для комфортного проживания мебелью и техникой. В стоимость включено машино место на подземном паркинге, лифт ведет сразу в подьед. К проживанию рассматривают строго одного человека либо семейную пару, , без питомцев и детей.Примечание у собственника могут быть дополнительные пожелания к жильцам  обсудите их в чате или по телефону", "sku": 322052883, "brand": {"@type": "Brand", "name": "Циан"}, "review": {"@type": "Review", "reviewRating": {"@type": "Rating", "ratingValue": 4.8, "bestRating": 5}, "author": {"@type": "Person", "name": ""}}, "offers": {"@type": "Offer", "url": "https://www.cian.ru/rent/flat/322052883/", "priceCurrency": "RUB", "availability": "https://schema.org/InStock", "price": 150000}}}, "trackingUrl": "/rent/flat/JK/obl_id=1/city_id=1/object_type=/ga_obj_type=1/rent_type=long/spec=agent/322052883/from_developer=0/repres=0/owner=0/pod_snos=0/nv=0/", "amenities": [{"title": "В квартире есть", "id": "flatRent", "amenities": [{"value": "Холодильник", "theme": "fridge"}, {"value": "Посудомоечная машина", "theme": "dishwasher"}, {"value": "Стиральная машина", "theme": "washing"}, {"value": "Кондиционер", "theme": "cond"}, {"value": "Телевизор", "theme": "tv"}, {"value": "Интернет", "theme": "internet"}, {"value": "Душевая кабина", "theme": "shower"}, {"value": "Мебель на кухне", "theme": "kitchen"}, {"value": "Мебель в комнатах", "theme": "furniture"}]}], "newbuildingRating": 0, "offerPrice": "150 000 ₽/мес.", "company": null}, "promotionsVillageData": {}, "offerStatsPopup": {"dataStats": null, "isOpen": false, "messageError": "", "statusFetch": 0}, "pageData": {"dealType": "rent", "offerId": 322052883, "offerType": "flat", "subdomain": "www"}, "phoneCollapse": false, "phoneWarning": {"isOpen": false, "target": null}, "printModal": {"isCommentsVisible": true, "isOpen": false, "isPhonesVisible": true, "isPrintModeEnabled": false}, "pushSubscribed": false, "reclaimModal": {"errorMessage": "", "isOpen": false, "statusFetch": "none"}, "remove": {"activeFrame": "initial", "isOpen": false, "status": "default"}, "seoLinks": {"isLoad": false, "seoLinks": {"seoBlocks": []}}, "serviceBaseUrl": "https://service.cian.ru/", "similarOffers": {"userBased": {"list": [], "withoutCompetitors": false, "modelVersion": ""}, "itemBased": {"list": [], "withoutCompetitors": false, "modelVersion": ""}, "historyBased": {"list": [], "withoutCompetitors": false, "modelVersion": ""}, "newItemBased": {"list": [], "withoutCompetitors": false, "modelVersion": ""}, "newobjectItemBased": {"list": [], "withoutCompetitors": false, "modelVersion": ""}}, "specialPromoInfo": null, "subscriptionPriceChangesPopup": {"error": "", "isEmailConfirmed": false, "isOpen": false, "statusFetch": "none"}, "tracking": {"user": {"abGroup": 0, "type": "not_authorized"}, "page": {"customPageURL": "/rent/flat/mo_id=0/obl_id=1/city_id=1/object_type=/ga_obj_type=1/rent_type=long/spec=agent/322052883/from_developer=0/repres=0/owner=0/pod_snos=0/nv=0/", "dealType": "rent_long", "objectType": "flat_old", "offerID": 322052883, "offerPhone": "+79858327697", "pageType": "Card", "region": "0-1-1", "siteType": "desktop", "breadCrumbs": ["Недвижимость в Москве", "Аренда", "Аренда 1-комнатных квартир в Москве", "СЗАО", "Хорошево-Мневники", "метро Шелепиха", "Шелепихинская набережная"], "extra": {"category": "flatRent", "adfox": {"status": 0}}}}, "viewedSimilar": {"ids": []}, "ebcInfo": {"user": {"abGroup": 0, "isAuthorized": false}, "page": {"breadCrumbs": ["Недвижимость в Москве", "Аренда", "Аренда 1-комнатных квартир в Москве", "СЗАО", "Хорошево-Мневники", "метро Шелепиха", "Шелепихинская набережная"], "offerID": 322052883}}, "mlSearchRegions": [], "isMlSearchForAllEnabled": true, "isBrandingAvailable": true, "isCountrysideOffersBuilderBadgeEnabled": true, "isHomeowner": false, "soprApi": "https://sopr-api.cian.ru/", "widgetsMarkup": {}, "infrastructureMap": {"isLoaded": false}, "infrastructureCategories": [], "isCountrysidePromoEnabled": true, "knAuctionCompanies": [], "auctionBanks": [], "dealRent": {"isOpen": false, "isLoading": false, "error": null, "isSuccessModal": false, "isSendSimilarModal": false, "isSimilarSuccessModal": false, "isFailureModal": false, "isPrefetching": false, "phoneConfirmed": false, "isSendSMSLoading": false, "secondsToRetry": 60, "isEntryToShowOpen": false, "isEntryToShowSuccessModal": false, "initialFormState": {"personsCount": 1, "personsInfo": "", "childrenCount": 0, "childrenInfo": [], "petsCount": 0, "petsInfo": "", "comment": "", "activityScope": "", "name": "", "isAgent": false, "phone": "", "smsCode": ""}}, "renterForm": {"isOpen": false, "isLoading": false, "error": null, "isSuccessModal": false, "isFailureModal": false, "isPrefetching": false, "phoneConfirmed": false, "isSendSMSLoading": false, "secondsToRetry": 60, "currentStep": "onboarding", "initialFormState": {"personsCount": 1, "personsInfo": "", "childrenCount": 0, "childrenInfo": [], "petsCount": 0, "petsInfo": "", "comment": "", "activityScope": "", "name": "", "isAgent": false, "phone": "", "smsCode": ""}}, "complaintPopupOpen": false, "notAvailablePopupOpen": false, "featureToggle": {"utilitiesTermsSettings": {"isUtilitiesTermsEnabled": true, "useIncludeUtilitiesTermsRegions": true, "excludeUtilitiesTermsRegions": [4959, 4606, 4588, 2], "includeUtilitiesTermsRegions": [1, 4593]}, "newbuildingBlackFridaySettings": {"promoDatesText": ""}, "isFavoritesFolderEnabled": true, "isBuyAnalyticsButtonEnabled": false, "isLegalDocsUrlForCommercialReportsEnabled": true, "isCommercialNewVatTextEnabled": true, "isMortgageBrokerBannerEnabled": true, "isBestPlaceCheckoutEnabled": true, "isChatOnboardingEnabled": true, "isMortgageCalculatorInObjectCardEnabled": true, "isMortgageCalculatorInSecondaryObjectCardEnabled": true, "isMortgageCalculatorInSuburbanCardEnabled": true, "isPurchaseTermsEnabled": true, "earlyAccessContactsFlowEnabled": true, "isNewbuildingBrokerFlatBannerEnabled": true}, "dealRentVasCost": 0, "isHomeownerDocsRequired": false, "offersHistory": {"data": {"listing": {"isFetching": false, "isError": false, "data": null, "isLoadMore": false}, "listingSpoiler": {"isFetching": false, "isError": false, "data": null, "isLoadMore": false}, "offers": {"isFetching": false, "isError": false, "isAuthError": false, "isLoadMore": false, "data": {}}}, "roomsFilterActiveValue": "all", "statusFilterActiveValue": "all", "page": 1, "resultsOnPage": 10, "activeOfferId": null, "isFiltersChanged": false, "viewedOffers": [], "defaultFilters": {}, "haveAdminAccess": false}, "offerValuation": {"data": null, "isFetching": false, "isError": false, "estimationPeriod": null}, "showAnalyticsButton": false, "entryToShowEnabled": false, "newStatsEnabled": false, "favoritesAssignWidget": {"folders": [], "selected": {}, "initialSelectedFolderIds": [], "savedOfferId": [], "savedInFolders": null, "userHasFolders": false, "showFoldersList": false, "showModalCreateFolder": false, "showOnBoardingDelete": false, "showNotification": false, "isListLoading": false, "canLoadMore": false}, "banksList": {"list": [{"id": "bank-sberbank", "enabled": false, "logo": "https://static.cdn-cian.ru/frontend/finance-assets/banks/logos/sber.svg", "icon": "https://static.cdn-cian.ru/frontend/finance-assets/bages/sber.svg", "name": "Сбербанк", "integration": "none"}, {"id": "bank-vtb-new", "enabled": true, "logo": "https://static.cdn-cian.ru/frontend/finance-assets/banks/logos/vtb.svg", "icon": "https://static.cdn-cian.ru/frontend/finance-assets/bages/vtb.svg", "fullsizeIcon": "https://static.cdn-cian.ru/frontend/finance-assets/fullsize/VTB_color.svg", "name": "ВТБ", "legalName": "Банк ВТБ (ПАО)", "integration": "custom", "inn": "7702070139"}, {"id": "bank-psb", "enabled": true, "logo": "https://static.cdn-cian.ru/frontend/finance-assets/banks/logos/psb.svg", "icon": "https://static.cdn-cian.ru/frontend/finance-assets/bages/psb.svg", "fullsizeIcon": "https://static.cdn-cian.ru/frontend/finance-assets/fullsize/PSB_color.svg", "name": "ПСБ", "legalName": "ПAO «Промсвязьбанк»", "integration": "light", "inn": "7744000912"}, {"id": "bank-gpb", "enabled": true, "logo": "https://static.cdn-cian.ru/frontend/finance-assets/banks/logos/gpb.svg", "icon": "https://static.cdn-cian.ru/frontend/finance-assets/bages/gazprom-bank.svg", "fullsizeIcon": "https://static.cdn-cian.ru/frontend/finance-assets/fullsize/GAZPROM_color.svg", "name": "Газпромбанк", "legalName": "Банк ГПБ (АО)", "integration": "light", "env": ["dev", "ote"], "inn": "7744001497"}, {"id": "bank-sovcom", "enabled": true, "logo": "https://static.cdn-cian.ru/frontend/finance-assets/banks/logos/sovcom.svg", "icon": "https://static.cdn-cian.ru/frontend/finance-assets/bages/sovkom-bank.svg", "fullsizeIcon": "https://static.cdn-cian.ru/frontend/finance-assets/fullsize/SOVKOMBANK_color.svg", "name": "Совкомбанк", "legalName": "ПАО «Совкомбанк»", "integration": "api", "inn": "4401116480"}, {"id": "bank-raif", "enabled": false, "logo": "https://static.cdn-cian.ru/frontend/finance-assets/banks/logos/raif.svg", "icon": "https://static.cdn-cian.ru/frontend/finance-assets/bages/raiffeisen-bank.svg", "fullsizeIcon": "https://static.cdn-cian.ru/frontend/finance-assets/fullsize/RAIFF_color.svg", "name": "Райффайзенбанк", "legalName": "АО «Райффайзенбанк»", "integration": "none", "inn": "7744000302"}, {"id": "bank-rshb", "enabled": false, "logo": "https://static.cdn-cian.ru/frontend/finance-assets/banks/logos/rshb.svg", "icon": "https://static.cdn-cian.ru/frontend/finance-assets/bages/rshb.svg", "fullsizeIcon": "https://static.cdn-cian.ru/frontend/finance-assets/fullsize/ROSSELHOZ_color.svg", "name": "Россельхозбанк", "legalName": "АО «Россельхозбанк»", "integration": "none", "inn": "7725114488"}, {"id": "bank-alfa", "enabled": true, "logo": "https://static.cdn-cian.ru/frontend/finance-assets/banks/logos/alfa.svg", "icon": "https://static.cdn-cian.ru/frontend/finance-assets/bages/alfa.svg", "fullsizeIcon": "https://static.cdn-cian.ru/frontend/finance-assets/fullsize/ALFA_color.svg", "name": "Альфа-Банк", "legalName": "АО «Альфа-Банк»", "integration": "light", "inn": "7728168971"}, {"id": "bank-bgf", "enabled": true, "logo": "https://static.cdn-cian.ru/frontend/finance-assets/banks/logos/bgf.svg", "icon": "https://static.cdn-cian.ru/frontend/finance-assets/bages/bgf.svg", "fullsizeIcon": "https://static.cdn-cian.ru/frontend/finance-assets/fullsize/BGF_color.svg", "name": "БЖФ", "notPayroll": true, "legalName": "АО «Банк БЖФ»", "integration": "api", "env": ["ote"], "inn": "7709056550"}, {"id": "bank-ubrir", "enabled": false, "logo": "https://static.cdn-cian.ru/frontend/finance-assets/banks/logos/ubrir.svg", "icon": "https://static.cdn-cian.ru/frontend/finance-assets/bages/ubrir.svg", "fullsizeIcon": "https://static.cdn-cian.ru/frontend/finance-assets/fullsize/UBRIR_color.svg", "name": "УБРиР", "legalName": "ПАО КБ «УБРИР»", "integration": "light", "inn": "6608008004"}, {"id": "bank-open", "enabled": false, "logo": "https://static.cdn-cian.ru/frontend/finance-assets/banks/logos/open.svg", "icon": "https://static.cdn-cian.ru/frontend/finance-assets/bages/open.svg", "fullsizeIcon": "https://static.cdn-cian.ru/frontend/finance-assets/fullsize/OPEN_color.svg", "name": "Открытие", "legalName": "ПАО Банк «ФК Открытие»", "integration": "none", "requireSpouseInfo": true, "inn": "7706092528"}, {"id": "bank-uralsib", "enabled": true, "logo": "https://static.cdn-cian.ru/frontend/finance-assets/banks/logos/uralsib.svg", "icon": "https://static.cdn-cian.ru/frontend/finance-assets/bages/uralsib.svg", "fullsizeIcon": "https://static.cdn-cian.ru/frontend/finance-assets/fullsize/URALSIB_color.svg", "name": "Уралсиб", "legalName": "ПАО «Банк Уралсиб»", "integration": "light", "inn": "0274062111"}, {"id": "bank-domrf", "enabled": true, "logo": "https://static.cdn-cian.ru/frontend/finance-assets/banks/logos/domrf.svg", "icon": "https://static.cdn-cian.ru/frontend/finance-assets/bages/domrf.svg", "fullsizeIcon": "https://static.cdn-cian.ru/frontend/finance-assets/fullsize/DOMRF_color.svg", "name": "Банк ДОМ.РФ", "legalName": "АО «Банк ДОМ.РФ", "integration": "light", "inn": "7725038124"}, {"id": "bank-domrf2", "enabled": true, "logo": "https://static.cdn-cian.ru/frontend/finance-assets/banks/logos/domrf.svg", "icon": "https://static.cdn-cian.ru/frontend/finance-assets/bages/domrf.svg", "fullsizeIcon": "https://static.cdn-cian.ru/frontend/finance-assets/fullsize/DOMRF_color.svg", "name": "Банк ДОМ.РФ Тест", "legalName": "АО «Банк ДОМ.РФ", "integration": "light", "env": ["ote"], "inn": "7725038124"}, {"id": "bank-t", "enabled": true, "logo": "https://static.cdn-cian.ru/frontend/finance-assets/banks/logos/tbank.svg", "icon": "https://static.cdn-cian.ru/frontend/finance-assets/bages/tbank.svg", "fullsizeIcon": "https://static.cdn-cian.ru/frontend/finance-assets/fullsize/TBANK_color.svg", "name": "Т-Банк", "legalName": "АО «ТБАНК»", "integration": "light", "inn": "7710140679"}, {"id": "bank-unicredit", "enabled": false, "logo": "https://static.cdn-cian.ru/frontend/finance-assets/banks/logos/unicredit.svg", "name": "ЮниКредит Банк", "integration": "none"}, {"id": "bank-mkb", "enabled": true, "logo": "https://static.cdn-cian.ru/frontend/finance-assets/banks/logos/mkb.svg", "icon": "https://static.cdn-cian.ru/frontend/finance-assets/bages/mkb.svg", "fullsizeIcon": "https://static.cdn-cian.ru/frontend/finance-assets/fullsize/MKB_color.svg", "name": "МКБ", "legalName": "ПАО «МКБ»", "integration": "light", "inn": "7734202860"}, {"id": "bank-personal-loan-emulator", "enabled": true, "logo": "https://static.cdn-cian.ru/frontend/finance-assets/banks/logos/bank-personal-loan-emulator.svg", "name": "Циан Банк", "integration": "api", "env": ["ote"]}, {"id": "bank-mts", "enabled": true, "logo": "https://static.cdn-cian.ru/frontend/finance-assets/banks/logos/mts.svg", "name": "МТС-Банк", "legalName": "ПАО «МТС-Банк»", "integration": "api", "env": ["ote"], "inn": "7702045051"}], "randomList": [{"id": "bank-uralsib", "enabled": true, "logo": "https://static.cdn-cian.ru/frontend/finance-assets/banks/logos/uralsib.svg", "icon": "https://static.cdn-cian.ru/frontend/finance-assets/bages/uralsib.svg", "fullsizeIcon": "https://static.cdn-cian.ru/frontend/finance-assets/fullsize/URALSIB_color.svg", "name": "Уралсиб", "legalName": "ПАО «Банк Уралсиб»", "integration": "light", "inn": "0274062111"}, {"id": "bank-mkb", "enabled": true, "logo": "https://static.cdn-cian.ru/frontend/finance-assets/banks/logos/mkb.svg", "icon": "https://static.cdn-cian.ru/frontend/finance-assets/bages/mkb.svg", "fullsizeIcon": "https://static.cdn-cian.ru/frontend/finance-assets/fullsize/MKB_color.svg", "name": "МКБ", "legalName": "ПАО «МКБ»", "integration": "light", "inn": "7734202860"}, {"id": "bank-vtb-new", "enabled": true, "logo": "https://static.cdn-cian.ru/frontend/finance-assets/banks/logos/vtb.svg", "icon": "https://static.cdn-cian.ru/frontend/finance-assets/bages/vtb.svg", "fullsizeIcon": "https://static.cdn-cian.ru/frontend/finance-assets/fullsize/VTB_color.svg", "name": "ВТБ", "legalName": "Банк ВТБ (ПАО)", "integration": "custom", "inn": "7702070139"}, {"id": "bank-t", "enabled": true, "logo": "https://static.cdn-cian.ru/frontend/finance-assets/banks/logos/tbank.svg", "icon": "https://static.cdn-cian.ru/frontend/finance-assets/bages/tbank.svg", "fullsizeIcon": "https://static.cdn-cian.ru/frontend/finance-assets/fullsize/TBANK_color.svg", "name": "Т-Банк", "legalName": "АО «ТБАНК»", "integration": "light", "inn": "7710140679"}]}, "mortgagePromoDesign": null, "flatTourBooking": {"isTooltipOpen": false, "schedule": null}, "crossedOutPriceExcludeNewbuildingIds": [6190, 7904, 8753, 30342, 2096941, 1611, 34895], "comparisonNotification": null, "rs": {"buyAnalyticsFreeReportData": {"name": "БЦ Саммит. Москва, Тверская улица, 22.", "date": "от 13.04.2022", "url": "https://static.cdn-cian.ru/frontend/iap-statics-frontend/others/demo-analytics-report.pdf"}, "buyAnalyticsLegalDocsUrl": "https://www.cian.ru/legal-documents/dogovor_publichnaya_oferta_ob_okazanii_uslugi_analiticheskij_otchet_informacionno_analiticheskoj_platformy_iap_v_vydache_marketplejsa_326", "bestPlaceAnalyticsReportExampleUrl": "https://cian.bestplace.pro/location-report/example.pdf?utm_source=bestplace-landingpro", "bestPlaceReportLegalDocsUrl": "https://www.cian.ru/legal-documents/dogovor_publichnaya_oferta_ob_okazanii_uslugi_otchet_o_privlekatelnosti_obekta_0", "bestPlaceReportBaseUrl": "https://cian.bestplace.pro/location-report", "bestPlaceReportProviderInfo": "Услугу предоставляет ООО «Бест-Плейс», ОГРН: 5167746245960", "isPerformanceVasPilot": true, "bookedFromDeveloperEnabled": true, "kpnChat": {"enabled": false, "availableRegionIds": [], "excludedNewbuildingIds": []}}, "isQaMode": false, "isRenterFormEnabled": true, "isScrollToCalculator": false, "buyAnalyticsModal": {"isOpened": false, "reportPrice": 0, "property": null, "status": null, "paymentUrl": null, "transactionId": null, "userEmail": "", "isReportAvailable": false, "openReportAfterAuth": false}, "bestPlaceModal": {"isOpened": false}, "recommendedVillages": null, "genplan": null, "adfoxOffer": {"response": {"status": "ok", "data": {"ymEvents": {"onPriceChange": null}, "dealType": "rent", "offerType": "flat", "params": {"puid1": "deal_type_rent", "puid2": "offer_flat", "puid36": 1, "puid4": "offer_type_1", "puid5": "obl_id_1", "puid6": "101_250", "puid7": "2323", "puid8": 150000, "puid9": 311, "puid10": "no_agent", "puid16": "false", "puid17": "false", "puid19": "not_video"}}}, "statusCode": 200}, "isStartChatWidgetInDropdown": false, "rosreestr": null, "bestPlaceAnalytics": {"amount": null, "discount": null, "discountPrice": null, "paymentUrl": null, "status": null, "statusMessage": null, "userEmail": null}, "buildersProjectsLocations": [], "suburbanBuildersProjects": [], "reviewsGoToAppModal": {"isOpen": false}, "valuationTraps": {"isMyHomeObjectsExists": false, "isEstimationExist": true}, "cpd": {"isCpdAvailable": false, "cpdDraftStatus": "init"}, "dailyrentBooking": {"general": {"isLoading": false, "price": "", "paymentSummary": null, "defaultBookingMessage": "", "error": ""}, "calendar": {"isOpen": false, "canBeBooked": true, "initialLoading": false, "daysAvailability": [], "showBookingCalendar": false, "dateInputText": "", "dates": {}}, "guests": {"isOpen": false, "guestsCount": 1, "minGuestsCount": 1, "maxGuestsCount": 99}}, "dailyrentActionType": null, "bannerRotation": 2, "comparison": {"comparison": {"props": [], "offers": [], "notFoundUrl": "/kupit-kvartiru/", "seoData": {"h1": "Сравнение квартир", "title": "Сравнение квартир в Москве - ЦИАН", "description": "Сравнение квартир в Москве по цене, площади и другим параметрам. Выбирайте на ЦИАН."}}}, "chatOnboarding": {"wasChatOpened": false}, "newbuildingBrokerOfferBooking": {"enabled": false, "callbackWidgetOpened": false, "galleryBannerAnalyticsSent": false, "loading": false, "bookingExistsModalOpened": false, "professionalAccessBlockedModalOpened": false}, "newbuildingExtraPrices": {"extraPrices": [], "linkedPromos": []}, "newbuildingBookedOfferLayouts": [], "bookedOfferRecommendations": [], "earlyAccessCounter": null}